Workbook

Sheet Venues
A1: VID | B1: Name | C1: Publisher | D1: Type
A3: 1 | B3: IEEE Transactions on Services Computing | C3: IEEE | D3: Journal
A4: 2 | B4: Journal of Grid Computing | C4: Springer | D4: Journal
A5: 3 | B5: IEEE Transactions on Parallel and Distributed Systems | C5: IEEE | D5: Journal
A6: 4 | B6: IEEE Transactions on Network and Service Management | C6: IEEE | D6: Journal
A7: 5 | B7: IEEE Access | C7: IEEE | D7: Journal
A8: 6 | B8: IEEE Transactions on Cloud Computing | C8: IEEE | D8: Journal
A9: 7 | B9: The Journal of Supercomputing | C9: Springer | D9: Journal
A10: 8 | B10: Computers and Industrial Engineering | C10: Elsevier | D10: Journal
A11: 9 | B11: Soft Computing | C11: Springer | D11: Journal
A12: 10 | B12: International Journal of Web Services Research | C12: IGI Global | D12: Journal
A13: 11 | B13: Future Generation Computer Systems | C13: Elsevier | D13: Journal
A14: 12 | B14: Journal of Ambient Intelligence and Humanized Computing | C14: Springer | D14: Journal
... A45: 43 | B45: International Conference on Service Science (CLOSER) | C45: Springer | D45: Conference

Sheet Papers
A1: PID | B1: VID | C1: Title | D1: Year | E1: Algorithm Name | F1: BibTex | G1: Publisher
A3: 1 | B3: =Venues!A3 -> 1 | C3: A Cloud Broker for Executing Deadline-Constrained Periodic Scientific Workflows | D3: 2023 | E3: cloud Broker for executing Deadline-constrained Periodic scientific Workflows (BDPW) | F3: article{1, author={Taheri, Hoda and Abrishami, Saeid and Naghibzadeh, Mahmoud}, journal={IEEE Transactions on Services Computing}, title={A Cloud Broker for Executing Deadline-Constrained Periodic Scientific Workflows}, year={2023}, volume={16}, number={5}, pages={3089-3100}, keywords={Task analysis;Cloud computing;Costs;Dynamic scheduling;Containers;Heuristic algorithms;Computational modeling;Cloud brokerage;periodic scientific workflows;multiple workflows scheduling;resource reservation;WaaS}, doi={10.1109/TSC.2023.3284492}} | G3: {=INDIRECT("Venues!C" & MATCH(B3,Venues!A:A,0))} -> IEEE
A4: 2 | B4: =Venues!A4 -> 2 | C4: A Cost-Efficient Workflow as a Service Broker Using On-demand and Spot Instances | D4: 2023 | E4: Cost Efficient Workflow-as-a-Service Broker (CEWB) | F4: article{2, author={Taghavi, Bahareh and Zolfaghari, Behrooz and Abrishami, Saeid}, journal={Journal of Grid Computing}, title={A Cost-Efficient Workflow as a Service Broker Using On-demand and Spot Instances}, year={2023}, volume={21}, number={40}, pages={}, doi={10.1007/s10723-023-09676-9}} | G4: {=INDIRECT("Venues!C" & MATCH(B4,Venues!A:A,0))} -> Springer
A5: 3 | B5: =Venues!A5 -> 3 | C5: Multi-Swarm Co-Evolution Based Hybrid Intelligent Optimization for Bi-Objective Multi-Workflow Scheduling in the Cloud | D5: 2022 | E5: Multi-swarm Co-evolution-based Hybrid intelligent Optimization (MCHO) | F5: article{3, author={Li, Huifang and Wang, Danjing and Zhou, MengChu and Fan, Yushun and Xia, Yuanqing}, journal={IEEE Transactions on Parallel and Distributed Systems}, title={Multi-Swarm Co-Evolution Based Hybrid Intelligent Optimization for Bi-Objective Multi-Workflow Scheduling in the Cloud}, year={2022}, volume={33}, number={9}, pages={2183-2197}, keywords={Task analysis;Cloud computing;Costs;Optimization;Heuristic algorithms;Quality of service;Dynamic scheduling;Cloud computing;intelligent optimization;multi-swarm;multiple workflows;Quality of Service (QoS);scheduling}, doi={10.1109/TPDS.2021.3122428}} | G5: {=INDIRECT("Venues!C" & MATCH(B5,Venues!A:A,0))} -> IEEE
A6: 4 | B6: =Venues!A3 -> 1 | C6: Uncertainty-Aware Online Scheduling for Real-Time Workflows in Cloud Service Environment | D6: 2018 | E6: unceRtainty-aware Online Scheduling Algorithm (ROSA) | F6: article{4, author={Chen, Huangke and Zhu, Xiaomin and Liu, Guipeng and Pedrycz, Witold}, journal={IEEE Transactions on Services Computing}, title={Uncertainty-Aware Online Scheduling for Real-Time Workflows in Cloud Service Environment}, year={2021}, volume={14}, number={4}, pages={1167-1178}, keywords={Task analysis;Cloud computing;Data transfer;Uncertainty;Schedules;Computer architecture;Scheduling;Workflow scheduling;uncertain;proactive and reactive strategies;cloud service}, doi={10.1109/TSC.2018.2866421}} | G6: {=INDIRECT("Venues!C" & MATCH(B6,Venues!A:A,0))} -> IEEE
A7: 5 | B7: =Venues!A3 -> 1 | C7: Resource Renting for Periodical Cloud Workflow Applications | D7: 2020 | E7: Precedence Tree-based Heuristic (PTH) | F7: article{5, author={Chen, Long and Li, Xiaoping and Ruiz, Rubén}, journal={IEEE Transactions on Services Computing}, title={Resource Renting for Periodical Cloud Workflow Applications}, year={2020}, volume={13}, number={1}, pages={130-143}, keywords={Cloud computing;Processor scheduling;Scheduling;Schedules;Quality of service;Minimization;Partitioning algorithms;Resource allocation;long-term resources renting;periodical multiple workflows;cloud computing}, doi={10.1109/TSC.2017.2677450}} | G7: {=INDIRECT("Venues!C" & MATCH(B7,Venues!A:A,0))} -> IEEE
A8: 6 | B8: =Venues!A6 -> 4 | C8: Real-Time Multiple-Workflow Scheduling in Cloud Environments | D8: 2021 | F8: article{6, author={Ma, Xiaojin and Xu, Huahu and Gao, Honghao and Bian, Minjie}, journal={IEEE Transactions on Network and Service Management}, title={Real-Time Multiple-Workflow Scheduling in Cloud Environments}, year={2021}, volume={18}, number={4}, pages={4002-4018}, keywords={Task analysis;Cloud computing;Processor scheduling;Costs;Real-time systems;Dynamic scheduling;Schedules;Cloud computing;multiple workflows;online scheduling;VM optimization}, doi={10.1109/TNSM.2021.3125395}} | G8: {=INDIRECT("Venues!C" & MATCH(B8,Venues!A:A,0))} -> IEEE
A9: 7 | B9: =Venues!A7 -> 5 | C9: Multi-Objective Workflow Scheduling With Deep-Q-Network-Based Multi-Agent Reinforcement Learning | D9: 2019 | E9: deep-Q-network based Multi Agent Reinforcement Learning (MARL) | F9: article{7, author={Wang, Yuandou and Liu, Hang and Zheng, Wanbo and Xia, Yunni and Li, Yawen and Chen, Peng and Guo, Kunyin and Xie, Hong}, journal={IEEE Access}, title={Multi-Objective Workflow Scheduling With Deep-Q-Network-Based Multi-Agent Reinforcement Learning}, year={2019}, volume={7}, number={}, pages={39974-39982}, keywords={Optimal scheduling;Games;Task analysis;Cloud computing;Reinforcement learning;Markov processes;Scheduling;Multi-objective workflow scheduling;deep-Q-network (DQN);multi-agent reinforcement learning (MARL);infrastructure-as-a-service (IaaS) cloud;quality-of-service (QoS)}, doi={10.1109/ACCESS.2019.2902846}} | G9: {=INDIRECT("Venues!C" & MATCH(B9,Venues!A:A,0))} -> IEEE
A10: 8 | B10: =Venues!A8 -> 6 | C10: Online Multi-Workflow Scheduling under Uncertain Task Execution Time in IaaS Clouds | D10: 2019 | E10: onliNe multi-wOrkflow Scheduling Framework (NOSF) | F10: article{8, author={Liu, Jiagang and Ren, Ju and Dai, Wei and Zhang, Deyu and Zhou, Pude and Zhang, Yaoxue and Min, Geyong and Najjari, Noushin}, journal={IEEE Transactions on Cloud Computing}, title={Online Multi-Workflow Scheduling under Uncertain Task Execution Time in IaaS Clouds}, year={2021}, volume={9}, number={3}, pages={1180-1194}, keywords={Task analysis;Cloud computing;Scheduling;Processor scheduling;Resource management;Stochastic processes;Pricing;Cloud computing;workflow scheduling;VM rental cost;uncertain task execution time;multiple workflows}, doi={10.1109/TCC.2019.2906300}} | G10: {=INDIRECT("Venues!C" & MATCH(B10,Venues!A:A,0))} -> IEEE
A11: 9 | B11: =Venues!A8 -> 6 | C11: Reliability, Rental-Cost and Energy-Aware Multi-Workflow Scheduling on Multi-Cloud Systems | D11: 2022 | E11: Reliability, rental cost and Energy-aware Multi-workflow Scheduling in the Multi-Cloud (REMSM) | F11: article{9, author={Taghinezhad-Niar, Ahmad and Taheri, Javid}, journal={IEEE Transactions on Cloud Computing}, title={Reliability, Rental-Cost and Energy-Aware Multi-Workflow Scheduling on Multi-Cloud Systems}, year={2023}, volume={11}, number={3}, pages={2681-2692}, keywords={Reliability;Cloud computing;Task analysis;Scheduling;Costs;Energy consumption;Behavioral sciences;Energy;multi-cloud;multi-workflow;reliability;scheduling}, doi={10.1109/TCC.2022.3223869}} | G11: {=INDIRECT("Venues!C" & MATCH(B11,Venues!A:A,0))} -> IEEE
A12: 10 | B12: =Venues!A9 -> 7 | C12: A cost and makespan aware scheduling algorithm for dynamic multi-workflow in cloud environment | D12: 2023 | E12: Multi-workflow scheduling Technology (MT) | F12: article{10, author={Xia, Yuanqing and Zhan, Yufeng and Dai, Li and Chen, Yuehong}, journal={The Journal of Supercomputing}, title={A cost and makespan aware scheduling algorithm for dynamic }, year={2023}, volume={79}, number={2}, pages={1814-1833}, doi={10.1007/s11227-022-04681-3}} | G12: {=INDIRECT("Venues!C" & MATCH(B12,Venues!A:A,0))} -> Springer
A13: 11 | B13: =Venues!A10 -> 8 | C13: Uncertainty-aware online deadline-constrained scheduling of parallel applications in distributed heterogeneous systems | D13: 2024 | E13: Online Parallel Applications Deadline-Constrained Scheduling algorithm (OPADCS) | F13: article{11, title = {Uncertainty-aware online deadline-constrained scheduling of parallel applications in distributed heterogeneous systems}, journal = {Computers & Industrial Engineering}, volume = {196}, pages = {110450}, year = {2024}, issn = {0360-8352}, doi = {https://doi.org/10.1016/j.cie.2024.110450}, url = {https://www.sciencedirect.com/science/article/pii/S0360835224005710}, author = {Yifan Liu and Jinchao Chen and Jiangong Yang and Chenglie Du and Xiaoyan Du}, keywords = {Online scheduling, Deadline constrained, Dynamic systems, Distributed heterogeneous systems, Uncertainty-aware}, abstract = {Parallel application scheduling with deadline constraints is a crucial area in distributed heterogeneous systems, and various methodologies have been proposed. However, these approaches overlook the uncertainty of task execution times and the randomness of application arrivals. Therefore, this study aims to solve the online scheduling problem of parallel applications with deadline constraints by introducing a novel algorithm that addresses uncertainties. We develop a model for randomly arriving applications and introduce a dynamic task prioritization strategy to mitigate uncertainty. Additionally, we augment with a discard mechanism to bolster application success rates. We conducted nine groups of experiments using both randomly generated applications and real-world applications. Simulation results demonstrate that the proposed algorithm significantly outperforms three similar algorithms in terms of enhancing DAG success rate, resource utilization, and runtime efficiency.} } | G13: {=INDIRECT("Venues!C" & MATCH(B13,Venues!A:A,0))} -> Elsevier
A14: 12 | B14: =Venues!A9 -> 7 | C14: Cost-efficient reactive scheduling for real-time workflows in clouds | D14: 2018 | E14: Cost-Efficient Reactive Scheduling Algorithm (CERSA) | F14: article{12, author={Chen, Huangke and Zhu, Jianghan and Wu, Guohua and Huo, Lisu}, journal={The Journal of Supercomputing}, title={Cost-efficient reactive scheduling for real-time workflows in clouds}, year={2018}, volume={74}, number={11}, pages={6291-6309}, doi={10.1007/s11227-018-2561-9}} | G14: {=INDIRECT("Venues!C" & MATCH(B14,Venues!A:A,0))} -> Springer
A15: 13 | B15: =Venues!A9 -> 7 | C15: A flexible deadline-driven resource provisioning and scheduling algorithm for multiple workflows with VM sharing protocol on WaaS-cloud | D15: 2022 | E15: Flexible Deadline-driven resource Provisioning and scheduling algorithm for Multiple workfows (FDPM) | F15: article{13, author={Rajasekar, P. and Palanichamy, Yogesh}, journal={The Journal of Supercomputing}, title={A flexible deadline-driven resource provisioning and scheduling algorithm for multiple workflows with VM sharing protocol on WaaS-cloud}, year={2022}, volume={78}, number={6}, pages={8025-8085}, doi={10.1007/s11227-021-04225-1}} | G15: {=INDIRECT("Venues!C" & MATCH(B15,Venues!A:A,0))} -> Springer
A16: 14 | B16: =Venues!A11 -> 9 | C16: Concurrent workflow budget- and deadline-constrained scheduling in heterogeneous distributed environments | D16: 2018 | E16: Multi-Workflow Heterogeneous Budget- and Deadline-Constrained Scheduling algorithm (MW-HBDCS) | F16: article{14, author={Zhou, Naqin and Li, FuFang and Xu, Kefu and Qi, Deyu}, journal={Soft Computing}, title={Concurrent workflow budget- and deadline-constrained scheduling in heterogeneous distributed environments}, year={2018}, volume={22}, number={23}, pages={7705-7718}, doi={10.1007/s00500-018-3229-3}} | G16: {=INDIRECT("Venues!C" & MATCH(B16,Venues!A:A,0))} -> Springer
A17: 15 | B17: =Venues!A9 -> 7 | C17: Fair multiple-workflow scheduling with different quality-of-service goals | D17: 2019 | F17: article{15, author={Rezaeian, Amin and Naghibzadeh, Mahmoud and Epema, Dick H. J.}, journal={The Journal of Supercomputing}, title={Fair multiple-workflow scheduling with different quality-of-service goals}, year={2019}, volume={75}, number={2}, pages={746-769}, doi={10.1007/s11227-018-2604-2}} | G17: {=INDIRECT("Venues!C" & MATCH(B17,Venues!A:A,0))} -> Springer
A18: 16 | B18: =Venues!A5 -> 3 | C18: Scheduling Periodical Multi-Stage Jobs With Fuzziness to Elastic Cloud Resources | D18: 2020 | E18: Fuzzy Dynamic Event Scheduling framework (FDES) and Fuzzy Task Scheduling (FTS) | F18: article{16, author={Zhu, Jie and Li, Xiaoping and Ruiz, Rubén and Li, Wei and Huang, Haiping and Zomaya, Albert Y.}, journal={IEEE Transactions on Parallel and Distributed Systems}, title={Scheduling Periodical Multi-Stage Jobs With Fuzziness to Elastic Cloud Resources}, year={2020}, volume={31}, number={12}, pages={2819-2833}, keywords={Task analysis;Dynamic scheduling;Job shop scheduling;Cloud computing;Schedules;Heuristic algorithms;Job scheduling;fuzzy processing times;fuzzy deadlines;cloud computing}, doi={10.1109/TPDS.2020.3004134}} | G18: {=INDIRECT("Venues!C" & MATCH(B18,Venues!A:A,0))} -> IEEE
A19: 17 | B19: =Venues!A12 -> 10 | C19: Scheduling Multi-Workflows Over Heterogeneous Virtual Machines With a Multi-Stage Dynamic Game-Theoretic Approach | D19: 2018 | E19: Multi-stage Dynamic Game-Theoretic (MDGT) | F19: article{17, author={Wu, Lei and Yuandou, Wang}, journal={International Journal of Web Services Research}, title={Scheduling Multi-Workflows Over Heterogeneous Virtual Machines With a Multi-Stage Dynamic Game-Theoretic Approach}, year={2018}, volume={15}, number={4}, pages={82-96}, doi={10.4018/IJWSR.2018100105}} | G19: {=INDIRECT("Venues!C" & MATCH(B19,Venues!A:A,0))} -> IGI Global
A20: 18 | B20: =Venues!A3 -> 1 | C20: Scheduling Constrained Cloud Workflow Tasks via Evolutionary Multitasking Optimization With Adaptive Knowledge Transfer | D20: 2024 | E20: Evolutionary Multitasking Constrained Optimization-Adaptive Double-level knowledge Transfer (EMCO-ADT) Evolutionary Multitasking Constrained Optimization-Adaptive Double-level knowledge Transfer (EMCO-ADT) | F20: article{18, author={Zhou, Jiajun and Gao, Liang and Rao, Shijie and Li, Yun}, journal={ IEEE Transactions on Services Computing }, title={{ Scheduling Constrained Cloud Workflow Tasks via Evolutionary Multitasking Optimization With Adaptive Knowledge Transfer }}, year={2024}, volume={17}, number={06}, ISSN={1939-1374}, pages={4254-4266}, abstract={ Cloud workflow scheduling (CWS) is critical for meeting user's high performance expectations in large-scale data processing and computing applications. CWS is known to be NP-hard and needs advanced scheduling techniques. Evolutionary algorithm and heuristic-based search techniques have gained massive popularity in addressing CWS, yet they either suffer from expensive computational cost or heavily rely on domain-specific experiences, which limit their practical applications. Bearing this in mind, we develop a novel evolutionary multi-task optimization framework to tackle a group of constrained CWS tasks simultaneously with the aid of adaptive cross-task problem-solving knowledge transfer. In particular, two collaborative knowledge exchange strategies, namely, constraint-free archive strategy and cross-task evolution strategy, are devised to extract useful building blocks from foreign tasks to boost the search efficiency. Further, to leverage the cooperative effects of both strategies, we develop an adaptive switching mechanism such that appropriate knowledge transfer strategies are learned automatically according to the population evolution status. Extensive experiments are conducted on real-world applications under various conditions, the comparison results show that our proposal delivers higher quality schedules than the state-of-the-art competitors in most cases. }, keywords={Processor scheduling;Search problems;Problem-solving;Optimal scheduling;Heuristic algorithms;Genetic algorithms;Costs}, doi={10.1109/TSC.2024.3463423}, url = {https://doi.ieeecomputersociety.org/10.1109/TSC.2024.3463423}, publisher={IEEE Computer Society}, address={Los Alamitos, CA, USA}, month=nov} | G20: {=INDIRECT("Venues!C" & MATCH(B20,Venues!A:A,0))} -> IEEE
A21: 19 | B21: =Venues!A13 -> 11 | C21: Scheduling dynamic workloads in multi-tenant scientific workflow as a service platforms | D21: 2018 | E21: Elastic resource Provisioning and Scheduling algorithm for Multiple workflows (EPSM) | F21: article{19, title = {Scheduling dynamic workloads in multi-tenant scientific workflow as a service platforms}, journal = {Future Generation Computer Systems}, volume = {79}, pages = {739-750}, year = {2018}, issn = {0167-739X}, doi = {https://doi.org/10.1016/j.future.2017.05.009}, url = {https://www.sciencedirect.com/science/article/pii/S0167739X17301681}, author = {Maria A. Rodriguez and Rajkumar Buyya}, keywords = {Cloud computing, Cost minimization, Deadline, Workflow as a service, Resource provisioning, Scheduling}, abstract = {With the advent of cloud computing and the availability of data collected from increasingly powerful scientific instruments, workflows have become a prevailing mean to achieve significant scientific advances at an increased pace. Emerging Workflow as a Service (WaaS) platforms offer scientists a simple, easily accessible, and cost-effective way of deploying their applications in the cloud at anytime and from anywhere. They are multi-tenant frameworks and are designed to manage the execution of a continuous workload of heterogeneous workflows. To achieve this, they leverage the compute, storage, and network resources offered by Infrastructure as a Service (IaaS) providers. Hence, at any given point in time, a WaaS platform should be capable of efficiently scheduling an arbitrarily large number of workflows with different characteristics and quality of service requirements. As a result, we propose a resource provisioning and scheduling strategy designed specifically for WaaS environments. The algorithm is scalable and dynamic to adapt to changes in the environment and workload. It leverages containers to address resource utilization inefficiencies and aims to minimize the overall cost of leasing the infrastructure resources while meeting the deadline constraint of each individual workflow. To the best of our knowledge, this is the first approach that explicitly addresses VM sharing in the context of WaaS by modeling the use of containers in the resource provisioning and scheduling heuristics. Our simulation results demonstrate its responsiveness to environmental uncertainties, its ability to meet deadlines, and its cost-efficiency when compared to a state-of-the-art algorithm.} } | G21: {=INDIRECT("Venues!C" & MATCH(B21,Venues!A:A,0))} -> Elsevier
A22: 20 | B22: =Venues!A13 -> 11 | C22: A multi-class workflow ensemble management system using on-demand and spot instances in cloud | D22: 2022 | E22: Multi-class Workflow Ensemble Sched_x0002_uling (MWEM) | F22: article{20, title = {A multi-class workflow ensemble management system using on-demand and spot instances in cloud}, journal = {Future Generation Computer Systems}, volume = {137}, pages = {97-110}, year = {2022}, issn = {0167-739X}, doi = {https://doi.org/10.1016/j.future.2022.07.007}, url = {https://www.sciencedirect.com/science/article/pii/S0167739X22002369}, author = {Behrooz Zolfaghari and Saeid Abrishami}, keywords = {Cloud computing, Resource provisioning, Task scheduling, Spot instances, Workflow ensemble, Scientific Workflows}, abstract = {Nowadays, cloud computing is an attractive and competitive market, and many computational jobs have migrated to cloud resources. Scheduling a workflow is a common issue in cloud computing. In some applications, a group of interrelated workflows with the same structure but different sizes and inputs is considered as a single job called an ensemble. Executing such applications in the cloud is expensive, and designing a cost-efficient approach is still challenging. The current paper proposes a new algorithm for scheduling workflow ensembles that are subject aware to of budget and deadline constraints. To achieve this aim, the present study takes advantage of Amazon spot instances. These instances are offered by bid at a lower price but with lower reliability. In the proposed algorithm, workflow tasks are classified according to deadlines and priorities, and the requested spot instances are classified based on bid prices. More reliable instances with higher bid prices are assigned to more important classes of tasks. Furthermore, an efficient workflow acceptance and instance provisioning procedure are proposed to launch and terminate instances based on the number of ready tasks and their deadlines. The present research’s simulation results show that the proposed system increases the number of completed workflows and reduces the number of partially executed ones.} } | G22: {=INDIRECT("Venues!C" & MATCH(B22,Venues!A:A,0))} -> Elsevier
A23: 21 | B23: =Venues!A13 -> 11 | C23: Algorithms for cost- and deadline-constrained provisioning for scientific workflow ensembles in IaaS clouds | D23: 2015 | E23: Dynamic Provisioning Dynamic Scheduling (DPDS) and Workflow Aware DPDS (WA-DPDS) | F23: article{21, title = {Algorithms for cost- and deadline-constrained provisioning for scientific workflow ensembles in IaaS clouds}, journal = {Future Generation Computer Systems}, volume = {48}, pages = {1-18}, year = {2015}, note = {Special Section: Business and Industry Specific Cloud}, issn = {0167-739X}, doi = {https://doi.org/10.1016/j.future.2015.01.004}, url = {https://www.sciencedirect.com/science/article/pii/S0167739X15000059}, author = {Maciej Malawski and Gideon Juve and Ewa Deelman and Jarek Nabrzyski}, keywords = {Scientific workflows, Workflow ensembles, Cloud computing, Resource provisioning}, abstract = {Large-scale applications expressed as scientific workflows are often grouped into ensembles of inter-related workflows. In this paper, we address a new and important problem concerning the efficient management of such ensembles under budget and deadline constraints on Infrastructure as a Service (IaaS) clouds. IaaS clouds are characterized by on-demand resource provisioning capabilities and a pay-per-use model. We discuss, develop, and assess novel algorithms based on static and dynamic strategies for both task scheduling and resource provisioning. We perform the evaluation via simulation using a set of scientific workflow ensembles with a broad range of budget and deadline parameters, taking into account task granularity, uncertainties in task runtime estimations, provisioning delays, and failures. We find that the key factor determining the performance of an algorithm is its ability to decide which workflows in an ensemble to admit or reject for execution. Our results show that an admission procedure based on workflow structure and estimates of task runtimes can significantly improve the quality of solutions.} } | G23: {=INDIRECT("Venues!C" & MATCH(B23,Venues!A:A,0))} -> Elsevier
A24: 21-b | E24: Static Provisioning Static Scheduling (SPSS)
A25: 22 | B25: =Venues!A14 -> 12 | C25: Scheduling multiple scientific workflows using containers on IaaS cloud | D25: 2021 | E25: Scalable Resource Provisioning and Scheduling algorithm for Multiple workfows (SRPSM) | F25: article{22, author={Rajasekar, P. and Palanichamy, Yogesh}, journal={Journal of Ambient Intelligence and Humanized Computing}, title={Scheduling multiple scientific workflows using containers on IaaS cloud}, year={2021}, volume={12}, number={7}, pages={7621-7636}, doi={10.1007/s12652-020-02483-0}} | G25: {=INDIRECT("Venues!C" & MATCH(B25,Venues!A:A,0))} -> Springer
A26: 23 | B26: =Venues!A13 -> 11 | C26: Dynamic multi-workflow scheduling: A deadline and cost-aware approach for commercial clouds | D26: 2019 | E26: Dynamic Workflow Scheduler (DWS) | F26: article{23, title = {Dynamic multi-workflow scheduling: A deadline and cost-aware approach for commercial clouds}, journal = {Future Generation Computer Systems}, volume = {100}, pages = {98-108}, year = {2019}, issn = {0167-739X}, doi = {https://doi.org/10.1016/j.future.2019.04.029}, url = {https://www.sciencedirect.com/science/article/pii/S0167739X18307386}, author = {Vahid Arabnejad and Kris Bubendorfer and Bryan Ng}, abstract = {Cloud computing, specifically its elastic, on demand, and pay per use instances, provide an ideal model for resourcing large scale state-of-the-art scientific analyses. Such scientific work is typically represented as workflows — the most common model for characterizing e-Science experiments and data analysis. Hosting and managing scientific applications on the cloud poses new challenges in terms of workflow scheduling which is key in leveraging its inherent cost and performance benefits. Prior research has studied static scheduling when the number of workflows is known in advance and all are submitted at the same time. However, in practice, a scheduler may have to schedule an unpredictable stream of workflows, for example, recent workflow management systems — such as Parsl, do not construct complete workflows at any stage during their execution, rather they generate partial workflows dynamically during execution — somewhat akin to lazy evaluation. This change in the way in which scientific data and workflows are created and processed represents a disruptive change to the way in which scheduling needs to occur. This paper represents a first and necessary step towards addressing scheduling problems of this nature, in which we present a new algorithm, Dynamic Workload Scheduler (DWS) that handles the dynamics of multiple deadline constrained workflows arriving randomly and scheduling these workflows with reducing cost in mind. Our results show that the DWS algorithm achieves an average 10% higher success rate in terms of fulfilling deadlines for different workloads and reduces the overall cost by an average 23% when compared to the most recent comparable algorithm.} } | G26: {=INDIRECT("Venues!C" & MATCH(B26,Venues!A:A,0))} -> Elsevier
A27: 24 | B27: =Venues!A15 -> 13 | C27: QoS-aware online scheduling of multiple workflows under task execution time uncertainty in clouds | D27: 2022 | E27: Energy and Uncertain task exection time aware workflow Scheduling Framework (EUSF) | F27: article{24, author={Taghinezhad-Niar, Ahmad and Pashazadeh, Saeid and Taheri, Javid}, journal={Cluster Computing}, title={QoS-aware online scheduling of multiple workflows under task execution time uncertainty in clouds}, year={2022}, volume={25}, number={6}, pages={3767-3784}, doi={10.1007/s10586-022-03600-8}} | G27: {=INDIRECT("Venues!C" & MATCH(B27,Venues!A:A,0))} -> Springer
A28: 25 | B28: =Venues!A16 -> 14 | C28: Cloud Computing: A Multi-workflow Scheduling Algorithm with Dynamic Reusability | D28: 2018 | E28: Competent Dynamic Multi-Workflow Scheduling (CDMWS) | F28: article{25, author={Adhikari, Mainak and Koley, Santanu}, journal={Arabian Journal for Science and Engineering}, title={Cloud Computing: A Multi-workflow Scheduling Algorithm with Dynamic Reusability}, year={2018}, volume={43}, number={2}, pages={645-660}, doi={10.1007/s13369-017-2739-0}} | G28: {=INDIRECT("Venues!C" & MATCH(B28,Venues!A:A,0))} -> Springer
A29: 26 | B29: =Venues!A17 -> 15 | C29: TOPSIS inspired Budget and Deadline Aware Multi-Workflow Scheduling for Cloud computing | D29: 2021 | E29: TOPSIS inspired Budget and Deadline aware Multi-Workflow Scheduling algorithm (T-BDMWS) | F29: article{26, title = {TOPSIS inspired Budget and Deadline Aware Multi-Workflow Scheduling for Cloud computing}, journal = {Journal of Systems Architecture}, volume = {114}, pages = {101916}, year = {2021}, issn = {1383-7621}, doi = {https://doi.org/10.1016/j.sysarc.2020.101916}, url = {https://www.sciencedirect.com/science/article/pii/S138376212030179X}, author = {Koneti Kalyan Chakravarthi and L. Shyamala}, keywords = {TOPSIS, Quality of service, Budget, Deadline, Scheduling, Multiple workflows}, abstract = {Scheduling is a decision-making mechanism that allows resource sharing among several activities by determining their order of execution on the available resources. In the heterogeneous distributed systems, it is a great challenge to schedule concurrent workflows submitted by different users at different times. Scheduling with deadline and budget constraints are becoming an even more challenging issue for cloud systems due to the cloud dynamics such as on-demand provisioning, elasticity, abundant resource types, and various pricing schemes. A well-managed budget and deadline constraint scheduling is required to optimize the system performance and end-user satisfaction. Hence, improving system performance and optimizing multiple scheduling criteria at the same time is a big challenge. To address these issues, a novel multi-workflow scheduling algorithm based on the Multi-Criteria Decision Making (MCDM) approach, TOPSIS (Technique of Order Preference by Similarity to Ideal Solution) is presented. A weighted sum of run time, cost and data transfer time are used to determine the optimal resource among the available resources in accordance with the task requirements. The performance of the proposed algorithm is compared with the state-of-the-art algorithms such as Budget-Heterogeneous Earliest Finish Time (BHEFT), Budget and Deadline Constraint Heterogeneous Earliest Finish Time (BDHEFT) and Cloud-based Workflow Scheduling Algorithm (CWSA) algorithms based on budget constraint,deadline constraint, and resource utilization. The experimental results demonstrate that the proposed T-BDMWS outperforms current state-of-the-art heuristics with the criteria of achieving the user-specified budget or deadline constraints and resource efficiency.} } | G29: {=INDIRECT("Venues!C" & MATCH(B29,Venues!A:A,0))} -> Elsevier
A30: 27 | B30: =Venues!A18 -> 16 | C30: Maximizing the completion rate of concurrent scientific applications under time and budget constraints | D30: 2017 | E30: Multi-Workflow Deadline-Budget Scheduling algorithm (MWDBS) | F30: article{27, title = {Maximizing the completion rate of concurrent scientific applications under time and budget constraints}, journal = {Journal of Computational Science}, volume = {23}, pages = {120-129}, year = {2017}, issn = {1877-7503}, doi = {https://doi.org/10.1016/j.jocs.2016.10.013}, url = {https://www.sciencedirect.com/science/article/pii/S1877750316302447}, author = {Hamid Arabnejad and Jorge G. Barbosa}, keywords = {Concurrent jobs, Workflow applications, Clouds, Grids}, abstract = {In many domains of science, scientific applications are represented by workflows. In this paper, we introduce a resource management strategy to maximize the success rate of concurrent workflow applications constrained by individual deadline and budget values. The Multi-Workflow Deadline-Budget Scheduling (MW-DBS) algorithm can schedule multiple workflows that can arrive in the system at any time, with the aim of satisfying individual job requirements. MW-DBS produces schedules without performing optimizations but guarantees that the deadline and budget defined for each job are not exceeded. Experimental results show that our strategy increases the scheduling success rate of finding valid solutions.} } | G30: {=INDIRECT("Venues!C" & MATCH(B30,Venues!A:A,0))} -> Elsevier
A31: 28 | B31: =Venues!A13 -> 11 | C31: Multi-QoS constrained and Profit-aware scheduling approach for concurrent workflows on heterogeneous systems | D31: 2017 | E31: Multi-QoS Profit-Aware Scheduling algorithm (MQ-PAS) | F31: article{28, title = {Multi-QoS constrained and Profit-aware scheduling approach for concurrent workflows on heterogeneous systems}, journal = {Future Generation Computer Systems}, volume = {68}, pages = {211-221}, year = {2017}, issn = {0167-739X}, doi = {https://doi.org/10.1016/j.future.2016.10.003}, url = {https://www.sciencedirect.com/science/article/pii/S0167739X16303740}, author = {Hamid Arabnejad and Jorge G. Barbosa}, keywords = {Quality of service, On-line scheduling, Deadline, Budget}, abstract = {The execution of a workflow application can result in an imbalanced workload among allocated processors, ultimately resulting in a waste of resources and a higher cost to the user. Here, we consider a dynamic resource management system in which processors are reserved not for a job but only to run a task, thus allowing a higher resource usage rate. This paper presents a scheduling algorithm that manages concurrent workflows in a dynamic environment in which jobs are submitted by users at any moment in time, on shared heterogeneous resources, and constrained to a specified budget and deadline for each job. Recent research attempted to propose dynamic strategies for concurrent workflows but only addressed fairness in resource sharing among applications while minimizing the execution time. The Multi-QoS Profit-Aware scheduling algorithm (MQ-PAS) proposed here is able to increase the profit achieved by the provider by considering the budget available for each job to define tasks priorities. We study the scalability of the algorithm with different types of workflows and infrastructures. The experimental results show that our strategy improves provider revenue significantly and obtains comparable successful rates of completed jobs.} } | G31: {=INDIRECT("Venues!C" & MATCH(B31,Venues!A:A,0))} -> Elsevier
A32: 29 | B32: =Venues!A19 -> 17 | C32: TOPSIS inspired cost-efficient concurrent workflow scheduling algorithm in cloud | D32: 2022 | E32: TOPSIS inspired Cost-efficient Concurrent Workflow Scheduling Algorithm (T-CCWSA) | F32: article{29, title = {TOPSIS inspired cost-efficient concurrent workflow scheduling algorithm in cloud}, journal = {Journal of King Saud University - Computer and Information Sciences}, volume = {34}, number = {6, Part A}, pages = {2359-2369}, year = {2022}, issn = {1319-1578}, doi = {https://doi.org/10.1016/j.jksuci.2020.02.006}, url = {https://www.sciencedirect.com/science/article/pii/S1319157820303207}, author = {K. Kalyan Chakravarthi and L. Shyamala and V. Vaidehi}, keywords = {TOPSIS, Quality of Service, Deadline, Scheduling, Concurrent Workflows}, abstract = {Scheduling is a decision-making mechanism that enables the sharing of resources among several activities by determining their execution order on the set of available resources. In distributed systems, it is a great challenge to schedule multiple workflows submitted at different times. In particular, concurrent workflow scheduling with time constraints makes the problem more complex in the cloud due to the dynamics of the cloud such as elasticity, non-homogeneous resource types, various pricing schemes, and virtualization. A well-managed deadline workflow scheduling is required to improve end-user satisfaction and system performance. In the meantime, the intrinsic uncertainty in the cloud increases the difficulties of scheduling problems. Therefore, it is a great challenge to improve system performance and optimize several scheduling criteria simultaneously. To address the above issues, a novel concurrent workflow scheduling method for heterogeneous distributed environments based on the new Multi-Criteria Decision Making (MCDM) method i.e., TOPSIS (Technique of Order Preference by Similarity to Ideal Solution) is presented. A weighted sum of execution time, cost and communication time are used to find out the optimal resource among the existing resources as per the workflow task requirements. The proposed method minimizes the makespan and execution cost of the workflow and improves the resource efficiency under uncertain environment. The performance of the proposed work is compared with the state-of-the-art algorithms such as Cloud-based Workflow Scheduling Algorithm (CWSA), Earliest Finish Time-Maximum Effective Reduction (EFT-MER) and Heterogeneous Earliest-Finish-Time (HEFT) algorithms based on deadline constraint and resource utilization. Our experimental results demonstrate that the proposed T-CCWSA outperforms current state-of-the-art heuristics with the criteria of achieving the deadline constraint, minimizing the cost of execution and resource efficiency.} } | G32: {=INDIRECT("Venues!C" & MATCH(B32,Venues!A:A,0))} -> Elsevier
A33: 30 | B33: =Venues!A20 -> 18 | C33: Uncertainty-aware scheduling of real-time workflows under deadline constraints on multi-cloud systems | D33: 2022 | E33: Real-time Workflows Scheduling on Multi-Cloud (RWSMC) | F33: article{30, author = {Xu, Jin and Yu, Huiqun and Fan, Guisheng and Zhang, Jiayin}, title = {Uncertainty-aware scheduling of real-time workflows under deadline constraints on multi-cloud systems}, journal = {Concurrency and Computation: Practice and Experience}, volume = {35}, number = {5}, pages = {e7562}, keywords = {cloud computing, real-time workflows, multi-cloud systems, uncertain task execution time}, doi = {https://doi.org/10.1002/cpe.7562}, url = {https://onlinelibrary.wiley.com/doi/abs/10.1002/cpe.7562}, eprint = {https://onlinelibrary.wiley.com/doi/pdf/10.1002/cpe.7562}, abstract = {Summary The elasticity and pay-as-you-go features of cloud computing are popular with customers, and more and more workflow applications are migrating to cloud platforms. Many workflow scheduling algorithms aim to obtain minimal rental costs. However, most of the existing research assumes that task execution time is deterministic. In fact, due to the performance fluctuations of VMs, the task execution time is uncertain before scheduling. Furthermore, many works ignore the cost savings given by multi-cloud systems. To this end, this paper provides a scheduling framework for real-time workflows. The framework includes four main components: the workflow analyzer, task pool, task allocation controller, and resource manager. Then based on the framework, we propose the RWSMC heuristic algorithm. The algorithm's goal is to minimize the total rental cost while satisfying the deadline constraints and ensuring the reliability of task execution. The RWSMC algorithm reduces the cost by selecting the appropriate billing mechanism based on the task's execution time and mitigates the impact of uncertain execution time by scheduling the task to the VM with the shortest predicted start time. Simulation experiments demonstrate that our proposed algorithm outperforms three recent state-of-the-art scheduling algorithms in the total rental cost, deadline violation rate, and VM resource utilization.}, year = {2023} } | G33: {=INDIRECT("Venues!C" & MATCH(B33,Venues!A:A,0))} -> Wiley
A34: 31 | B34: =Venues!A21 -> 19 | C34: Versatile provisioning and workflow scheduling in WaaS under cost and deadline constraints for cloud computing | D34: 2018 | F34: article{31, author = {Partheeban, Pon. and Kavitha, V.}, title = {Versatile provisioning and workflow scheduling in WaaS under cost and deadline constraints for cloud computing}, journal = {Transactions on Emerging Telecommunications Technologies}, volume = {30}, number = {1}, pages = {e3527}, doi = {https://doi.org/10.1002/ett.3527}, url = {https://onlinelibrary.wiley.com/doi/abs/10.1002/ett.3527}, eprint = {https://onlinelibrary.wiley.com/doi/pdf/10.1002/ett.3527}, note = {e3527 ETT-18-0242.R1}, abstract = {Abstract Cloud computing environment delivers resources and services via a pay-as-you-go billing model, and scheduling workflows have become a major application for distributed systems. An efficient scheduling is very challenging in a cloud to achieve minimum overhead, low cost, and high utilization of resources within the deadline. Workflow as a service (WaaS) provides a simple cost successive way to use the workflow applications in the cloud. This paper introduces a Gang of Tasks (GoTs)–based dynamic scheduling technique for scheduling the workflow to reduce the cost of renting virtual machines (VMs) under the deadline constraints in the WaaS environment. First, the GoTs strategy groups the workflows based on the priority and dependency of data. It schedules similar tasks into the same gang to execute the task from the gang simultaneously to the VMs. After scheduling the task in the GoTs, the deadline is distributed among all the gangs in the workflow. Then, the versatile resources are provisioned, dynamically depending upon the usage of containers in the VMs. The simulation results validate the ability to satisfy the deadline constraints and cost deficiencies of the proposed method as compared to the state-of-the-art methods.}, year = {2019} } | G34: {=INDIRECT("Venues!C" & MATCH(B34,Venues!A:A,0))} -> Wiley
A35: 32 | B35: =Venues!A22 -> 20 | C35: Multi-criteria scheduling of scientific workflows in the Workflow as a Service platform | D35: 2023 | E35: Multi-Criteria Scientific Workflows (MCSW) | F35: article{32, title = {Multi-criteria scheduling of scientific workflows in the Workflow as a Service platform}, journal = {Computers and Electrical Engineering}, volume = {105}, pages = {108458}, year = {2023}, issn = {0045-7906}, doi = {https://doi.org/10.1016/j.compeleceng.2022.108458}, url = {https://www.sciencedirect.com/science/article/pii/S0045790622006735}, author = {Anurina Tarafdar and Kamalesh Karmakar and Rajib K Das and Sunirmal Khatua}, keywords = {Workflow, Container, Energy, Workflow as a service (WaaS), Cloud computing, Resource scheduling}, abstract = {The increasing use of workflows in various fields of science has led to the development of the Workflow as a Service (WaaS) platform, which provides workflow execution as a service to the users. The WaaS platform must use appropriate resource provisioning, sharing, and scheduling, to properly allocate the workflow tasks to the Cloud resources and fulfill the scheduling objectives. In this paper, we have proposed a novel workflow scheduling approach for the WaaS platform that reduces the average makespan of the workflows, improves energy efficiency, and reduces the resource renting cost of the Cloud resources. Our scheduling model consists of containers, virtual machines (VMs), and hosts. We have also proposed a suitable scaling policy for the Cloud resources to improve resource utilization. Extensive simulations with real-world workflows and comparison with some state-of-the-art algorithms show the efficacy of our approach in improving performance and energy efficiency while reducing the monetary cost.} } | G35: {=INDIRECT("Venues!C" & MATCH(B35,Venues!A:A,0))} -> Elsevier
A36: 33 | B36: =Venues!A15 -> 13 | C36: Weighted double deep Q-network based reinforcement learning for bi-objective multi-workflow scheduling in the cloud | D36: 2022 | E36: Weighted Double Deep Q-Network based Reinforcement Learning algorithm (WDDQN-RL) | F36: article{33, author={Li, Huifang and Huang, Jianghang and Wang, Binyang and Fan, Yushun}, journal={Cluster Computing}, title={Weighted double deep Q-network based reinforcement learning for bi-objective multi-workflow scheduling in the cloud}, year={2022}, volume={25}, number={2}, pages={751-768}, doi={10.1007/s10586-021-03454-6}} | G36: {=INDIRECT("Venues!C" & MATCH(B36,Venues!A:A,0))} -> Springer
A37: 34 | B37: =Venues!A15 -> 13 | C37: Security prioritized multiple workflow allocation model under precedence constraints in cloud computing environment | D37: 2024 | E37: Security Prioritized Multiple Workflow Allocation (SPMWA) | F37: article{34, author={Alam, Mahfooz and Shahid, Mohammad and Mustajab, Suhel}, journal={Cluster Computing}, title={Security prioritized multiple workflow allocation model under precedence constraints in cloud computing environment}, year={2024}, volume={27}, number={1}, pages={341-376}, doi={10.1007/s10586-022-03819-5}} | G37: {=INDIRECT("Venues!C" & MATCH(B37,Venues!A:A,0))} -> Springer
A38: 35 | B38: =Venues!A15 -> 13 | C38: Trust-driven and QoS demand clustering analysis based cloud workflow scheduling strategies | D38: 2014 | F38: article{35, author={Li, Wenjuan and Wu, Jiyi and Zhang, Qifei and Hu, Keyong and Li, Jing}, journal={Cluster Computing}, title={Trust-driven and QoS demand clustering analysis based cloud workflow scheduling strategies}, year={2014}, volume={17}, number={3}, pages={1013-1030}, doi={10.1007/s10586-013-0340-1}} | G38: {=INDIRECT("Venues!C" & MATCH(B38,Venues!A:A,0))} -> Springer
A39: 36 | B39: =Venues!A32 -> 30 | C39: Clustering-based multi-objective optimization considering fairness for multi-workflow scheduling on clouds | D39: 2024 | E39: Depth-First-Search considering Critical Subsequent Task(DFS-CST) | F39: article{36, title = {Clustering-based multi-objective optimization considering fairness for multi-workflow scheduling on clouds}, journal = {Journal of Parallel and Distributed Computing}, volume = {194}, pages = {104968}, year = {2024}, issn = {0743-7315}, doi = {https://doi.org/10.1016/j.jpdc.2024.104968}, url = {https://www.sciencedirect.com/science/article/pii/S0743731524001321}, author = {Feng Li and Wen Jun Tan and Moon Gi Seok and Wentong Cai}, keywords = {Multi-objective optimization, Multi-workflow scheduling, Scheduling fairness, Clustering-based resource allocation}, abstract = {Distributed computing, such as cloud computing, provides promising platforms for orchestrating scientific workflows' tasks based on their sequences and dependencies. Workflow scheduling plays an important role in optimizing concerned objectives for distributed computing, such as minimizing the makespan and cost. Many researchers have focused on optimizing a specific single workflow with multiple objectives. Currently, there are few studies on multi-workflow scheduling, with most research focusing on objectives such as cost and makespan. However, multi-workflow scheduling requires the design of specific objectives that reflect the unique characteristics of multiple workflows. On the other hand, clustering-based approaches have garnered significant attention in the field of workflow scheduling over distributed computing resources due to their advantage in reducing data communication among tasks. Despite this, the effectiveness of clustering-based algorithms has not been extensively studied and validated in the context of multi-objective multi-workflow scheduling models. Motivated by these factors, we propose an approach for multiple workflows' multi-objective optimization (MOO), considering the new defined metric, fairness. We first mathematically formulate the fairness and define a fairness-involved MOO model. Then, we propose an advanced clustering-based resource optimization strategy in multiple workflow runs. Experimental results show that the proposed approach performs better than the compared algorithms without significant compromise of the overall makespan and cost as well as individual fairness, which can guide the simulation workflow scheduling on clouds.} } | G39: {=INDIRECT("Venues!C" & MATCH(B39,Venues!A:A,0))} -> Elsevier
A40: 37 | B40: =Venues!A23 -> 21 | C40: WaaS: Workflow-as-a-Service for the Cloud with Scheduling of Continuous and Data-Intensive Workflows | D40: 2016 | E40: sidering Critical Subsequent Task (DFS-CST) | F40: article{37, author = {Esteves, Sergio and Veiga, Lui­s}, title = "{WaaS: Workflow-as-a-Service for the Cloud with Scheduling of Continuous and Data-Intensive Workflows}", journal = {The Computer Journal}, volume = {59}, number = {3}, pages = {371-383}, year = {2015}, month = {01}, abstract = "{Data-intensive and long-lasting applications running in the form of workflows are being increasingly dispatched to cloud computing systems. Current scheduling approaches for graphs of dependencies fail to deliver high resource efficiency while keeping computation costs low, especially for continuous data processing workflows, where the scheduler does not perform any reasoning about the impact new input data may have in the workflow final output. To face such a challenge, we introduce a new scheduling criterion, Quality-of-Data (QoD), which describes the requirements about the data that are worthy of the triggering of tasks in workflows. Based on the QoD notion, we propose a novel service-oriented scheduler planner, for continuous data processing workflows, that is capable of enforcing QoD constraints and guide the scheduling to attain resource efficiency, overall controlled performance and task prioritization. To contrast the advantages of our scheduling model against others, we developed WaaS (Workflow-as-a-Service), a workflow coordinator system for the Cloud where data is shared among tasks via cloud columnar database.}", issn = {0010-4620}, doi = {10.1093/comjnl/bxu158}, url = {https://doi.org/10.1093/comjnl/bxu158}, eprint = {https://academic.oup.com/comjnl/article-pdf/59/3/371/7902553/bxu158.pdf}, } | G40: {=INDIRECT("Venues!C" & MATCH(B40,Venues!A:A,0))} -> Oxford Academic
A41: 38 | B41: =Venues!A24 -> 22 | C41: Dynamic Scheduling Stochastic Multiworkflows With Deadline Constraints in Clouds | D41: 2023 | E41: Stochastic Multi-Workflows Dynamic Scheduling Algorithm (SMWDSA) | F41: article{38, author={Ye, Lingjuan and Xia, Yuanqing and Yang, Liwen and Zhan, Yufeng}, journal={IEEE Transactions on Automation Science and Engineering}, title={Dynamic Scheduling Stochastic Multiworkflows With Deadline Constraints in Clouds}, year={2023}, volume={20}, number={4}, pages={2594-2606}, keywords={Task analysis;Cloud computing;Costs;Dynamic scheduling;Job shop scheduling;Heuristic algorithms;Schedules;Dynamic scheduling;multi-workflows;deadline constraints;cloud computing}, doi={10.1109/TASE.2022.3204313}} | G41: {=INDIRECT("Venues!C" & MATCH(B41,Venues!A:A,0))} -> IEEE
A42: 39 | B42: =Venues!A26 -> 24 | C42: Enhancing generalization in genetic programming hyper-heuristics through mini-batch sampling strategies for dynamic workflow scheduling | D42: 2024 | E42: Genetic Programming Hyper-Heuristics with an instance Sampling strategy (GPHHS) | F42: article{39, author={Fan, Guisheng and Chen, Xingpeng and Li, Zengpeng and Yu, Huiqun and Zhang, Yingxue}, journal={IEEE Transactions on Network and Service Management}, title={An Energy-Efficient Dynamic Scheduling Method of Deadline-Constrained Workflows in a Cloud Environment}, year={2023}, volume={20}, number={3}, pages={3089-3103}, keywords={Task analysis;Energy consumption;Cloud computing;Costs;Resource management;Virtual machining;Dynamic scheduling;Task scheduling;deadline;energy consumption;resource utilization;cloud}, doi={10.1109/TNSM.2022.3228402}} | G42: {=INDIRECT("Venues!C" & MATCH(B42,Venues!A:A,0))} -> Elsevier
A43: 40 | B43: =Venues!A7 -> 5 | C43: Levelized Multiple Workflow Allocation Strategy Under Precedence Constraints With Task Merging in IaaS Cloud Environment | D43: 2022 | E43: Levelized Multiple Workflow allocation Strategy with Task Merging (LMWS-TM) | F43: article{40, author={Ahmad, Faisal and Shahid, Mohammad and Alam, Mahfooz and Ashraf, Zubair and Sajid, Mohammad and Kotecha, Ketan and Dhiman, Gaurav}, journal={IEEE Access}, title={Levelized Multiple Workflow Allocation Strategy Under Precedence Constraints With Task Merging in IaaS Cloud Environment}, year={2022}, volume={10}, number={}, pages={92809-92827}, keywords={Task analysis;Resource management;Cloud computing;Quality of service;Dynamic scheduling;Costs;Cloud computing;IaaS cloud environment;multiple workflow allocation;task merging;levelized DAG scheduling;turnaround time}, doi={10.1109/ACCESS.2022.3202651}} | G43: {=INDIRECT("Venues!C" & MATCH(B43,Venues!A:A,0))} -> IEEE
A44: 41 | B44: =Venues!A9 -> 7 | C44: DDBWS: a dynamic deadline and budget-aware workflow scheduling algorithm in workflow-as-a-service environments | D44: 2021 | E44: Dynamic, Deadline and Budget-aware, Workfow Scheduling (DDBWS) | F44: article{41, author={Saeedizade, Ehsan and Ashtiani, Mehrdad}, journal={The Journal of Supercomputing}, title={DDBWS: a dynamic deadline and budget-aware workflow scheduling algorithm in workflow-as-a-service environments}, year={2021}, volume={77}, number={12}, pages={14525-14564}, doi={10.1007/s11227-021-03858-6}} | G44: {=INDIRECT("Venues!C" & MATCH(B44,Venues!A:A,0))} -> Springer
A45: 42 | B45: =Venues!A9 -> 7 | C45: Real-time workflows oriented online scheduling in uncertain cloud environment | D45: 2017 | E45: Event-Driven and Periodic Rolling Strategies (EDPRS) | F45: article{42, author={Chen, Huangke and Zhu, Jianghan and Zhang, Zhenshi and Ma, Manhao and Shen, Xin}, journal={The Journal of Supercomputing}, title={Real-time workflows oriented online scheduling in uncertain cloud environment}, year={2017}, volume={73}, number={11}, pages={4906-4922}, doi={10.1007/s11227-017-2060-4}} | G45: {=INDIRECT("Venues!C" & MATCH(B45,Venues!A:A,0))} -> Springer
A46: 43 | B46: =Venues!A25 -> 23 | C46: Constructing Reliable Computing Environments on Top of Amazon EC2 Spot Instances | D46: 2020 | E46: MISER | F46: article{43, AUTHOR = {Sampaio, Altino M. and Barbosa, Jorge G.}, TITLE = {Constructing Reliable Computing Environments on Top of Amazon EC2 Spot Instances}, JOURNAL = {Algorithms}, VOLUME = {13}, YEAR = {2020}, NUMBER = {8}, ARTICLE-NUMBER = {187}, URL = {https://www.mdpi.com/1999-4893/13/8/187}, ISSN = {1999-4893}, ABSTRACT = {Cloud provider Amazon Elastic Compute Cloud (EC2) gives access to resources in the form of virtual servers, also known as instances. EC2 spot instances (SIs) offer spare computational capacity at steep discounts compared to reliable and fixed price on-demand instances. The drawback, however, is that the delay in acquiring spots can be incredible high. Moreover, SIs may not always be available as they can be reclaimed by EC2 at any given time, with a two-minute interruption notice. In this paper, we propose a multi-workflow scheduling algorithm, allied with a container migration-based mechanism, to dynamically construct and readjust virtual clusters on top of non-reserved EC2 pricing model instances. Our solution leverages recent findings on performance and behavior characteristics of EC2 spots. We conducted simulations by submitting real-life workflow applications, constrained by user-defined deadline and budget quality of service (QoS) parameters. The results indicate that our solution improves the rate of completed tasks by almost 20%, and the rate of completed workflows by at least 30%, compared with other state-of-the-art algorithms, for a worse-case scenario.}, DOI = {10.3390/a13080187} } | G46: {=INDIRECT("Venues!C" & MATCH(B46,Venues!A:A,0))} -> MDPI
A47: 44 | B47: =Venues!A33 -> 31 | C47: A collaborative multi-objective meta-heuristic for deadline-constrained multi-workflows scheduling in cloud environment | D47: 2024 | E47: Collaborative Multi-Objective Meta-Heuristic (CMOMH) | F47: article{44, title = {A collaborative multi-objective meta-heuristic for deadline-constrained multi-workflows scheduling in cloud environment}, journal = {Engineering Applications of Artificial Intelligence}, volume = {142}, pages = {109907}, year = {2025}, issn = {0952-1976}, doi = {https://doi.org/10.1016/j.engappai.2024.109907}, url = {https://www.sciencedirect.com/science/article/pii/S0952197624020669}, author = {Shuo Qin and Zhongshi Shao}, keywords = {Multi-workflows scheduling, Meta-heuristic, Multi-objective optimization, Deadline constraint, Cloud computing}, abstract = {As cloud computing technology rapidly advances, various organizations are increasingly migrating their complex workflow applications to cloud platforms. Given the diverse demands of users, multi-objective scheduling for multiple workflows has become both necessary and challenging. To tackle the deadline-constrained multi-objective multi-workflows scheduling problem, this paper introduces a collaborative multi-objective meta-heuristic (CMOMH), aiming to optimize a set of schedules that adhere to deadline constraint of each workflow while minimizing total execution time and cost. Within CMOMH, a bi-population co-evolutionary mechanism is crafted to prevent information exchange between feasible and infeasible schedules. A constraint-aware objective function is employed to evaluate infeasible schedules, and a differential evolution-based framework is leveraged to optimize the feasible ones. To maintain the task-to-virtual machine mapping, a sampling-based crossover operator is utilized to explore non-dominated schedules using a multi-point crossover strategy and a probability model. Additionally, two perturbation operators are integrated to enhance population diversity. Simulation results reveal that CMOMH significantly outperforms related state-of-the-art algorithms at the 95% confidence level, demonstrating its effectiveness in addressing the multi-objective scheduling challenges in cloud environments.} } | G47: {=INDIRECT("Venues!C" & MATCH(B47,Venues!A:A,0))} -> Elsevier
A48: 45 | B48: =Venues!A5 -> 3 | C48: Workflow Scheduling in Multi-Tenant Cloud Computing Environments | D48: 2017 | E48: Cloud-based Workflow Scheduling Algorithm (CWSA) | F48: article{45, author={Rimal, Bhaskar Prasad and Maier, Martin}, journal={IEEE Transactions on Parallel and Distributed Systems}, title={Workflow Scheduling in Multi-Tenant Cloud Computing Environments}, year={2017}, volume={28}, number={1}, pages={290-304}, keywords={Cloud computing;Processor scheduling;Resource management;Computer architecture;Scalability;Dynamic scheduling;Cloud computing;direct acyclic graph;multi-tenancy;resource management;scientific workflow applications}, doi={10.1109/TPDS.2016.2556668}} | G48: {=INDIRECT("Venues!C" & MATCH(B48,Venues!A:A,0))} -> IEEE
A49: 46 | B49: =Venues!A27 -> 25 | C49: Chaotic-Nondominated-Sorting Owl Search Algorithm for Energy-Aware Multi-Workflow Scheduling in Hybrid Clouds | D49: 2022 | E49: Chaotic-nondominated-sorting Owl Search Algorithm (COSA) | F49: article{46, author={Li, Huifang and Xu, Guanghao and Wang, Danjing and Zhou, MengChu and Yuan, Yan and Alabdulwahab, Ahmed}, journal={IEEE Transactions on Sustainable Computing}, title={Chaotic-Nondominated-Sorting Owl Search Algorithm for Energy-Aware Multi-Workflow Scheduling in Hybrid Clouds}, year={2022}, volume={7}, number={3}, pages={595-608}, keywords={Cloud computing;Scheduling;Processor scheduling;Costs;Task analysis;Quality of service;Particle swarm optimization;Multi-workflow scheduling;Hybrid clouds;Energy consumption;Owl search algorithm;Chaotic operator}, doi={10.1109/TSUSC.2022.3144357}} | G49: {=INDIRECT("Venues!C" & MATCH(B49,Venues!A:A,0))} -> IEEE
A50: 47 | B50: =Venues!A13 -> 11 | C50: Co-evolutionary and Elite learning-based bi-objective Poor and Rich Optimization algorithm for scheduling multiple workflows in the cloud | D50: 2024 | E50: Co-evolutionary and Elite learning-based bi-objective Poor and Rich Optimization algorithm (CE-PRO) | F50: article{47, title = {Co-evolutionary and Elite learning-based bi-objective Poor and Rich Optimization algorithm for scheduling multiple workflows in the cloud}, journal = {Future Generation Computer Systems}, volume = {152}, pages = {99-111}, year = {2024}, issn = {0167-739X}, doi = {https://doi.org/10.1016/j.future.2023.10.015}, url = {https://www.sciencedirect.com/science/article/pii/S0167739X23003898}, author = {Huifang Li and Luzhi Tian and Guanghao Xu and Julio Ruben {Cañizares Abreu} and Shuangxi Huang and Senchun Chai and Yuanqing Xia}, keywords = {Cloud computing, Meta-heuristics, Multi-objective optimization, Workflows, Scheduling, Poor and rich optimization algorithm}, abstract = {Cloud computing is a cost-effective environment for deploying large-scale scientific applications. However, multi-workflow scheduling has great challenge since users may request a series of applications with different Quality of Service (QoS) at the same time. In this paper, a Co-evolutionary and Elite learning-based bi-objective Poor and Rich Optimization algorithm (CE-PRO) is proposed for scheduling applications to minimize the makespan and cost of each workflow. First, an MPMO framework is combined with PRO to optimize two objectives by two populations, respectively for better balancing the search diversity and convergence speed, where each population is updated by an improved PRO, which adopts the middle-class sub-population and re-defines the update mechanism for rich individuals to enhance search diversity and reduce the possibility of falling into local optima. Second, to restrain each population focusing overly on its respective objective, a global information exchange pool is innovatively designed to save the non-dominated solutions ever found, which will be used back as the shared guiding solutions to foster inter-population communication and co-evolution during an evolutionary process. Third, a hybrid mutation-based Elite Enhancement Strategy (EES) is developed by introducing multiple scales of mutation operations into elite solutions alternatively and iteratively to exploit excellent individuals and explore more trade-off solutions. Extensive experiments are conducted on real world scientific workflows with different types and scales, and the experimental results demonstrate that in most cases, our proposed CE-PRO outperforms its peers in the number of obtained non-dominated solutions, and the solution diversity and quality as well. In particular, the dominance of CE-PRO is superior to its peers by at least 25.62%.} } | G50: {=INDIRECT("Venues!C" & MATCH(B50,Venues!A:A,0))} -> Elsevier
A51: 48 | B51: =Venues!A28 -> 26 | C51: Dual-mutation mechanism-driven snake optimizer for scheduling multiple budget constrained workflows in the cloud | D51: 2023 | E51: Dual-mutation Mechanism-driven Snake Optimizer (DM-SO) | F51: article{48, title = {Dual-mutation mechanism-driven snake optimizer for scheduling multiple budget constrained workflows in the cloud}, journal = {Applied Soft Computing}, volume = {149}, pages = {110966}, year = {2023}, issn = {1568-4946}, doi = {https://doi.org/10.1016/j.asoc.2023.110966}, url = {https://www.sciencedirect.com/science/article/pii/S1568494623009845}, author = {Huifang Li and Guanghao Xu and Boyuan Chen and Shuangxi Huang and Yuanqing Xia and Senchun Chai}, keywords = {Snake optimizer, Workflows, Scheduling, Cloud computing}, abstract = {Scheduling workflows in cloud computing is to find the most appropriate mapping from a series of dependent tasks to a set of available virtual resources so as to minimize or maximize some user concerned objectives, which is very significant to a sustainable and high-efficient cloud data center. However, it still faces challenges since its NP-hardness and the diversified requirements of both the cloud service consumers and cloud service providers need to be satisfied at the same time, especially in addressing multiple applications requested simultaneously. This work proposes a dual-mutation mechanism-driven snake optimizer for scheduling multiple workflows in the cloud for minimizing the makespan of each workflow under user pre-defined budget constraints. Firstly, a continuous optimization algorithm, namely Snake Optimizer (SO) is adopted into discrete optimization, i.e., workflow scheduling. Secondly, a task execution order aware fitness function is designed to reduce the gaps or waiting time between parent and child tasks within a workflow and thus reduce the total execution time of the workflow. Besides, we analyze the existing snake optimizer and adjust the parameters corresponding to different evolutionary stages to adapt to our considered problem. Finally, a dual-mutation mechanism is developed by introducing a non-improvement iteration number for each snake and applying a standard bit mutation operation to prematurely converging snakes and the individuals randomly selected from the remaining snakes so that the population diversity can be enhanced and more potential solutions can be explored. Experimental results on a set of real-world scientific workflows show that our proposed algorithm is of great superiority in constraint satisfiability, meaning that compared with its peers, it is always the first to find feasible solutions.} } | G51: {=INDIRECT("Venues!C" & MATCH(B51,Venues!A:A,0))} -> Elsevier
A52: 49 | B52: =Venues!A29 -> 27 | C52: Efficient, economical and energy-saving multi-workflow scheduling in hybrid cloud | D52: 2023 | E52: Multi-objective Salp swarm Iterative greedy Algorithm (MSIA) | F52: article{49, title = {Efficient, economical and energy-saving multi-workflow scheduling in hybrid cloud}, journal = {Expert Systems with Applications}, volume = {228}, pages = {120401}, year = {2023}, issn = {0957-4174}, doi = {https://doi.org/10.1016/j.eswa.2023.120401}, url = {https://www.sciencedirect.com/science/article/pii/S095741742300903X}, author = {Zaixing Sun and Hejiao Huang and Zhikai Li and Chonglin Gu and Ruitao Xie and Bin Qian}, keywords = {Hybrid cloud, Multi-workflow scheduling, Directed acyclic graph, Heuristic algorithm, Multi-objective optimization, Pareto front}, abstract = {Benefiting from the flexible, scalable and secure environment, hybrid cloud can overcome the shortage of limited resources in private cloud to simultaneously execute large-scale scientific workflows. In hybrid cloud, privacy-sensitive tasks are not allowed to be executed on public resources, while non-sensitive tasks are unrestricted. As an NP-Complete problem, it is extraordinarily challenging to schedule multiple workflows efficiently, economically and energy-savingly under quality-of-service constraints. This paper models the hybrid-cloud-based privacy-aware multi-workflow scheduling as a tri-objective optimization problem that optimizes workflow-oriented total tardiness, private-cloud-oriented total energy consumption, and public-cloud-oriented total monetary cost. To the best of authors’ knowledge, few studies have been conducted on the tri-objective privacy-aware multi-workflow scheduling in hybrid cloud (PMWS-HC). To solve this problem, we dissect various factors involved during task scheduling and devise a novel Heuristic Scheduling Algorithm based on 9 Factors (HSA9Fs), which dynamically selects the workflows and tasks to be scheduled, and the corresponding VMs to execute them. To optimize the three conflicting objectives simultaneously, we propose a nested algorithm called MSIA, which first employs a Multi-objective Salp swarm algorithm to explore for the Pareto solutions, and then uses an Iterative greedy Algorithm to perform a refined search on individuals to obtain high-quality solutions. Extensive Medium-Small-Scale and Large-Scale simulation experiments show that both HSA9Fs and MSIA outperform state-of-the-art scheduling algorithms in several multi-objective performance metrics.} } | G52: {=INDIRECT("Venues!C" & MATCH(B52,Venues!A:A,0))} -> Elsevier
A53: 49-b | E53: Heuristic Scheduling Algorithm based on 9 Factors (HSA9Fs)
A54: 50 | B54: =Venues!A9 -> 7 | C54: Clustering-assisted gradient-based optimizer for scheduling parallel cloud workflows with budget constraints | D54: 2024 | E54: Clustering-assisted Gradient-Based Optimizer (C-GBO) | F54: article{50, author={Li, Huifang and Chen, Boyuan and Huang, Jingwei and Song, Zhuoyue and Xia, Yuanqing}, journal={The Journal of Supercomputing}, title={Clustering-assisted gradient-based optimizer for scheduling parallel cloud workflows with budget constraints}, year={2024}, volume={80}, number={12}, pages={17097-17034}, doi={10.1007/s11227-024-06114-9}} | G54: {=INDIRECT("Venues!C" & MATCH(B54,Venues!A:A,0))} -> Springer
A55: 51 | B55: =Venues!A7 -> 5 | C55: Adaptive Resource Allocation and Consolidation for Scientific Workflow Scheduling in Multi-Cloud Environments | D55: 2020 | E55: Online Workflow Scheduling algorithm based on Adaptive resource Allocation and Consolidation (OWS-A2C) | F55: article{51, author={Chen, Zheyi and Lin, Kai and Lin, Bing and Chen, Xing and Zheng, Xianghan and Rong, Chunming}, journal={IEEE Access}, title={Adaptive Resource Allocation and Consolidation for Scientific Workflow Scheduling in Multi-Cloud Environments}, year={2020}, volume={8}, number={}, pages={190173-190183}, keywords={Task analysis;Resource management;Scheduling;Cloud computing;Pricing;Scheduling algorithms;Multi-cloud environments;scientific workflows;scheduling optimization;resource allocation;resource consolidation}, doi={10.1109/ACCESS.2020.3032545}} | G55: {=INDIRECT("Venues!C" & MATCH(B55,Venues!A:A,0))} -> IEEE
A56: 52 | B56: =Venues!A31 -> 29 | C56: Dynamic Multiworkflow Deadline and Budget Constrained Scheduling in Heterogeneous Distributed Systems | D56: 2021 | E56: Dynamic MultiWorkflow Heterogeneous Deadline and Budget-constrained Scheduling (DMW-HDBS) | F56: article{52, author={Wang, Guan and Wang, Yuxin and Obaidat, Mohammad S. and Lin, Chi and Guo, He}, journal={IEEE Systems Journal}, title={Dynamic Multiworkflow Deadline and Budget Constrained Scheduling in Heterogeneous Distributed Systems}, year={2021}, volume={15}, number={4}, pages={4939-4949}, keywords={Task analysis;Dynamic scheduling;Heuristic algorithms;Quality of service;Heterogeneous networks;Resource management;Scheduling algorithms;Budget constrained;concurrent workflows;deadline constrained;dynamic scheduling systems;heterogeneous distributed system}, doi={10.1109/JSYST.2021.3087527}} | G56: {=INDIRECT("Venues!C" & MATCH(B56,Venues!A:A,0))} -> IEEE
A57: 53 | B57: =Venues!A30 -> 28 | C57: Scheduling ensemble workflows on hybrid resources in IaaS clouds | D57: 2024 | E57: Rules-based scheduling heuristic with hybrid provisioning (RBSHP) | F57: article{53, author={Chen, Long and Liu, Guangrui and Zhang, Jinquan and Zhang, Xiaodon}, journal={Computing}, title={Scheduling ensemble workflows on hybrid resources in IaaS clouds}, year={2024}, volume={107}, number={1}, pages={22}, doi={10.1007/s00607-024-01386-8}} | G57: {=INDIRECT("Venues!C" & MATCH(B57,Venues!A:A,0))} -> Springer
A58: 54 | B58: =Venues!A8 -> 6 | C58: Monetary Cost Optimizations for Hosting Workflow-as-a-Service in IaaS Clouds | D58: 2016 | E58: Dyna | F58: article{54, author={Zhou, Amelie Chi and He, Bingsheng and Liu, Cheng}, journal={IEEE Transactions on Cloud Computing}, title={Monetary Cost Optimizations for Hosting Workflow-as-a-Service in IaaS Clouds}, year={2016}, volume={4}, number={1}, pages={34-48}, keywords={Probabilistic logic;Optimization;Cloud computing;Dynamic scheduling;Quality of service;Heuristic algorithms;Interference;Cloud computing,;cloud dynamics,;spot prices,;monetary cost optimizations;scientific workflows;Cloud computing;cloud dynamics;spot prices;monetary cost optimizations;scientific workflows}, doi={10.1109/TCC.2015.2404807}} | G58: {=INDIRECT("Venues!C" & MATCH(B58,Venues!A:A,0))} -> IEEE
A59: 55 | B59: =Venues!A5 -> 3 | C59: A Declarative Optimization Engine for Resource Provisioning of Scientific Workflows in Geo-Distributed Clouds | D59: 2017 | E59: Geco | F59: article{55, author={Zhou, Amelie Chi and He, Bingsheng and Cheng, Xuntao and Lau, Chiew Tong}, journal={IEEE Transactions on Parallel and Distributed Systems}, title={A Declarative Optimization Engine for Resource Provisioning of Scientific Workflows in Geo-Distributed Clouds}, year={2017}, volume={28}, number={3}, pages={647-661}, keywords={Cloud computing;Optimization;Engines;Asia;Complexity theory;Probabilistic logic;Runtime;Resource provisioning;scientific workflows;declarative optimizations;geo-distributed clouds}, doi={10.1109/TPDS.2016.2599529}} | G59: {=INDIRECT("Venues!C" & MATCH(B59,Venues!A:A,0))} -> IEEE
A60: 56 | B60: =Venues!A7 -> 5 | C60: Genetic-Based Two Granularity Ordering Methods for Multiple Workflow Scheduling | D60: 2024 | F60: article{56, author={Li, Feng and Tan, Wen Jun and Seok, Moon Gi and Cai, Wentong}, journal={IEEE Access}, title={Genetic-Based Two Granularity Ordering Methods for Multiple Workflow Scheduling}, year={2024}, volume={12}, number={}, pages={1747-1760}, keywords={Task analysis;Costs;Scheduling;Resource management;Optimization;Clustering algorithms;Quality of service;Cloud computing;Cloud computing;multi-workflow;multi-objective optimization;task ordering;cluster ordering}, doi={10.1109/ACCESS.2023.3337832}} | G60: {=INDIRECT("Venues!C" & MATCH(B60,Venues!A:A,0))} -> IEEE
A61: 57 | B61: =Venues!A3 -> 1 | C61: Multi-Tree Genetic Programming Hyper-Heuristic for Dynamic Flexible Workflow Scheduling in Multi-Clouds | D61: 2024 | E61: Multi-Tree Genetic Programming (MTGP) | F61: article{57, author={Sun, Zaixing and Mei, Yi and Zhang, Fangfang and Huang, Hejiao and Gu, Chonglin and Zhang, Mengjie}, journal={IEEE Transactions on Services Computing}, title={Multi-Tree Genetic Programming Hyper-Heuristic for Dynamic Flexible Workflow Scheduling in Multi-Clouds}, year={2024}, volume={}, number={}, pages={1-16}, keywords={Dynamic scheduling;Cloud computing;Task analysis;Costs;Heuristic algorithms;Processor scheduling;Genetic programming;Dynamic workflow scheduling;multi-clouds;genetic programming;hyper-heuristic;deadline constraint}, doi={10.1109/TSC.2024.3394691}} | G61: {=INDIRECT("Venues!C" & MATCH(B61,Venues!A:A,0))} -> IEEE
A62: 58 | B62: =Venues!A4 -> 2 | C62: Cost-efficient Workflow as a Service using Containers | D62: 2024 | F62: article{58, author={Karmakar, Kamalesh and Tarafdar, Anurina and Das, Rajib K. and Khatua, Sunirmal}, journal={Journal of Grid Computing}, title={Cost-efficient Workflow as a Service using Containers}, year={2024}, volume={22}, number={1}, pages={40-}, doi={10.1007/s10723-024-09745-7}} | G62: {=INDIRECT("Venues!C" & MATCH(B62,Venues!A:A,0))} -> Springer
A63: 59 | B63: =Venues!A29 -> 27 | C63: A deep reinforcement learning-based scheduling framework for real-time workflows in the cloud environment | D63: 2024 | E63: Regularization - Deep Q-Network (R-DQN) | F63: article{59, title = {A deep reinforcement learning-based scheduling framework for real-time workflows in the cloud environment}, journal = {Expert Systems with Applications}, volume = {255}, pages = {124845}, year = {2024}, issn = {0957-4174}, doi = {https://doi.org/10.1016/j.eswa.2024.124845}, url = {https://www.sciencedirect.com/science/article/pii/S0957417424017123}, author = {Jiahui Pan and Yi Wei}, keywords = {Cloud computing, Multiple workflows, Real-time scheduling, Deep reinforcement learning, WorkflowSim}, abstract = {Benefiting from the flexibility, scalability and many other advantages of cloud computing, an increasing number of research institutions and enterprises are using cloud platforms to deploy their scientific or commercial workflow applications. From the perspective of cloud service providers, how to schedule workflows reasonably to improve user satisfaction and resource utilization is a big challenge. This challenge becomes more prominent in a dynamic cloud environment, where the workload of user-submitted workflows is constantly changing and unpredictable. Traditional scheduling methods designed for fixed workflows or real-time independent tasks are not applicable in such scenarios. In this paper, we present an online scheduling framework for multiple real-time workflows in a dynamic environment. In this framework, the scheduler employs a deep reinforcement learning based algorithm (R-DQN) to assign each task in workflows to a suitable virtual machine instance according to the current situation. Its goal is to achieve optimal task scheduling and resource allocation, so as to minimize workflow makespan and maximize resource utilization. We provide a comprehensive overview of the design and implementation of our approach, and we conduct experiments using various workflow benchmarks with different structures and scales on the WorkflowSim platform. The experimental results demonstrate that our algorithm significantly outperforms the compared algorithms in term of makespan and other metrics. Moreover, our algorithm demonstrates strong performance in generality, robustness and scalability.} } | G63: {=INDIRECT("Venues!C" & MATCH(B63,Venues!A:A,0))} -> Elsevier
A64: 60 | B64: =Venues!A29 -> 27 | C64: Cost-aware scheduling systems for real-time workflows in cloud: An approach based on Genetic Algorithm and Deep Reinforcement Learning | D64: 2023 | E64: Genetic Algorithm - Deep Q-Network (GA-DQN) | F64: article{60, title = {Cost-aware scheduling systems for real-time workflows in cloud: An approach based on Genetic Algorithm and Deep Reinforcement Learning}, journal = {Expert Systems with Applications}, volume = {234}, pages = {120972}, year = {2023}, issn = {0957-4174}, doi = {https://doi.org/10.1016/j.eswa.2023.120972}, url = {https://www.sciencedirect.com/science/article/pii/S0957417423014744}, author = {Jingwei Zhang and Long Cheng and Cong Liu and Zhiming Zhao and Ying Mao}, keywords = {Workflow scheduling, Cloud computing, Deep Reinforcement Learning, Deep Q-learning, Genetic Algorithm}, abstract = {With the development of cloud computing, a growing number of applications are migrating to a cloud environment. In the process, the real-time scheduling of workflows has gradually become a technical challenge, due to the dynamic and uncertain nature of cloud environments and the complex dependencies between sub-tasks of the workflow. Although various methods have been reported up to now, these methods have their respective shortcomings, such as heuristic-based methods are hard to find optimal scheduling scheme and metaheuristic-based methods incur high computational overhead, which often lead to the violation of QoS (Quality of Service) requirements and increases service renting costs of executing workflows. Inspired by the successful application of Deep Reinforcement Learning (DRL) in cloud job scheduling, this paper proposes a real-time workflow scheduling method which combines Genetic Algorithm (GA) and DRL, aiming to reduce both execution cost and response time. To be specific, we design a real-time workflow scheduling algorithm named GA-DQN by combining the global search capability of GA and the environment awareness decision-making capability of DRL to divides scheduling process into two stages. First, the execution scheme of workflow in virtual machine is calculated when workflow arrives. Then, a DRL agent uses this scheme as the feature of workflow to assign workflow to a suitable virtual machine. In this way, the use of DRL to sense environment increases the computational efficiency of GA, and the execution scheme obtained by GA helps DRL to obtain the feature of workflow. On this basis of real world workflow, three groups of simulation experience are carried out to compare GA-DQN with four baseline method which consist of three traditional methods and a state-of-the-art method. The comparison results demonstrate that GA-DQN outperforms the other methods in terms of response time, execution cost, and success rate across different workloads and cloud instance configurations.} } | G64: {=INDIRECT("Venues!C" & MATCH(B64,Venues!A:A,0))} -> Elsevier
A65: 61 | B65: =Venues!A34 -> 32 | C65: Workflow as a Service in the Cloud: Architecture and Scheduling Algorithms | D65: 2014 | F65: article{61, title = {Workflow as a Service in the Cloud: Architecture and Scheduling Algorithms}, journal = {Procedia Computer Science}, volume = {29}, pages = {546-556}, year = {2014}, note = {2014 International Conference on Computational Science}, issn = {1877-0509}, doi = {https://doi.org/10.1016/j.procs.2014.05.049}, url = {https://www.sciencedirect.com/science/article/pii/S1877050914002269}, author = {Jianwu Wang and Prakashan Korambath and Ilkay Altintas and Jim Davis and Daniel Crawl}, keywords = {Workflow, Cloud, Workflow as a Service (WFaaS) architecture, workflow scheduling algorithms}, abstract = {With more and more workflow systems adopting cloud as their e xecution environment, it becomes increasingly challenging on how to effic iently manage various workflows, v irtual machines (VMs) and workflow e xecution on VM instances. To make the system scalable and easy-to-extend, we design a Workflow as a Service (WFaaS) a rchitecture with independent services. A core part of the architecture is how to efficiently respond continuous workflo w requests from users and schedule their e xecutions in the c loud. Based on diffe rent targets, we p ropose four heuristic workflo w scheduling a lgorith ms for the WFaaS architecture, and analy ze the differences and best usages of the algorith ms in terms of performance, cost and the price/performance ratio via experimental studies.} } | G65: {=INDIRECT("Venues!C" & MATCH(B65,Venues!A:A,0))} -> Elsevier
A66: 62 | B66: =Venues!A35 -> 33 | C66: A Framework for Automated Parallel Execution of Scientific Multi-workflow Applications in the Cloud with Work Stealing | D66: 2024 | F66: inproceedings{62, author="Silva, Helena S. I. L. and Castro, Maria C. S. and Silva, Fabricio A. B. and Melo, Alba C. M. A.", editor="Carretero, Jesus and Shende, Sameer and Garcia-Blas, Javier and Brandic, Ivona and Olcoz, Katzalin and Schreiber, Martin", title="A Framework for Automated Parallel Execution of Scientific Multi-workflow Applications in the Cloud with Work Stealing", booktitle="Euro-Par 2024: Parallel Processing", year="2024", publisher="Springer Nature Switzerland", address="Cham", pages="298--311", abstract="In this paper, we propose and evaluate an MPI/OpenMP framework to execute cloud applications composed of scientific linear multi-workflows with unknown task execution times and substantial I/O activity. In order to achieve load balancing, our framework incorporates a two-level work stealing strategy, with intra-node and inter-node stealing. The framework was evaluated in a cluster of 16 virtual machine (VM) instances (4 vCPUs), deployed on AWS Parallel Cluster. The results show that, for a real Bioinformatics application composed of 400 workflows, we are able to reduce the execution time from 1 h and 57 min (sequential) to 2 min and 52 s (16 instances), achieving a speedup of 40.89x, with 64 threads.", isbn="978-3-031-69583-4" } | G66: {=INDIRECT("Venues!C" & MATCH(B66,Venues!A:A,0))} -> Springer
A67: 63 | B67: =Venues!A36 -> 34 | C67: Cost-Aware Dynamic Cloud Workflow Scheduling Using Self-attention and Evolutionary Reinforcement Learning | D67: 2024 | E67: Self attention Policy Network for Cloud Workflow Scheduling (SPN-CWS) | F67: inproceedings{63, author="Shen, Ya and Chen, Gang and Ma, Hui and Zhang, Mengjie", editor="Gaaloul, Walid and Sheng, Michael and Yu, Qi and Yangui, Sami", title="Cost-Aware Dynamic Cloud Workflow Scheduling Using Self-attention and Evolutionary Reinforcement Learning", booktitle="Service-Oriented Computing", year="2025", publisher="Springer Nature Singapore", address="Singapore", pages="3--18", abstract="As a key cloud management problem, Cost-aware Dynamic Multi-Workflow Scheduling (CDMWS) aims to assign virtual machine (VM) instances to execute tasks in workflows so as to minimize the total costs, including both the penalties for violating Service Level Agreement (SLA) and the VM rental fees. Powered by deep neural networks, Reinforcement Learning (RL) methods can construct effective scheduling policies for solving CDMWS problems. Traditional policy networks in RL often use basic feedforward architectures to separately determine the suitability of assigning any VM instances, without considering all VMs simultaneously to learn their global information. This paper proposes a novel self-attention policy network for cloud workflow scheduling (SPN-CWS) that captures global information from all VMs. We also develop an Evolution Strategy-based RL (ERL) system to train SPN-CWS reliably and effectively. The trained SPN-CWS can effectively process all candidate VM instances simultaneously to identify the most suitable VM instance to execute every workflow task. Comprehensive experiments show that our method can noticeably outperform several state-of-the-art algorithms on multiple benchmark CDMWS problems.", isbn="978-981-96-0808-9" } | G67: {=INDIRECT("Venues!C" & MATCH(B67,Venues!A:A,0))} -> Springer
A68: 64 | B68: =Venues!A37 -> 35 | C68: A Fuzzy Scheduling Strategy for Online Multi-workflows in IaaS Clouds | D68: 2022 | E68: Workflow Fuzzy Scheduling Algorithm (WFSA) | F68: inproceedings{64, author={Ye, Lingjuan and Xia, Yuanqing and Yang, Liwen and Wu, Chu-Ge and Zhan, Yufeng}, booktitle={2022 41st Chinese Control Conference (CCC)}, title={A Fuzzy Scheduling Strategy for Online Multi-workflows in IaaS Clouds}, year={2022}, volume={}, number={}, pages={2428-2433}, keywords={Cloud computing;Schedules;Costs;Scheduling algorithms;Heuristic algorithms;Scheduling;Virtual machining;Workflow scheduling;Fuzzy processing time;Deadline constraint;Cloud computing}, doi={10.23919/CCC55666.2022.9902489}} | G68: {=INDIRECT("Venues!C" & MATCH(B68,Venues!A:A,0))} -> IEEE
A69: 65 | B69: =Venues!A38 -> 36 | C69: Uncertainty-Aware Real-Time Workflow Scheduling in the Cloud | D69: 2016 | E69: Proactive Reactive Scheduling (PRS) | F69: inproceedings{65, author={Chen, Huangke and Zhu, Xiaomin and Qiu, Dishan and Liu, Ling}, booktitle={2016 IEEE 9th International Conference on Cloud Computing (CLOUD)}, title={Uncertainty-Aware Real-Time Workflow Scheduling in the Cloud}, year={2016}, volume={}, number={}, pages={577-584}, keywords={Cloud computing;Scheduling;Uncertainty;Computer architecture;Schedules;Scheduling algorithms}, doi={10.1109/CLOUD.2016.0082}} | G69: {=INDIRECT("Venues!C" & MATCH(B69,Venues!A:A,0))} -> IEEE
A70: 66 | B70: =Venues!A39 -> 37 | C70: Online Multiple Workflow Scheduling under Privacy and Deadline in Hybrid Cloud Environment | D70: 2014 | E70: Online scheduling for Privacy in Hybrid Clouds using Task Ranking (OPHC-TR) and Online Multiterminal Cut for Privacy in Hybrid Clouds using PCP Ranking (OMPHC-PCPR). | F70: inproceedings{66, author={Sharif, Shaghayegh and Taheri, Javid and Zomaya, Albert Y. and Nepal, Surya}, booktitle={2014 IEEE 6th International Conference on Cloud Computing Technology and Science}, title={Online Multiple Workflow Scheduling under Privacy and Deadline in Hybrid Cloud Environment}, year={2014}, volume={}, number={}, pages={455-462}, keywords={Privacy;Cloud computing;Processor scheduling;Dynamic scheduling;Schedules;Heuristic algorithms;multiple workflow scheduling;Hybrid Cloud;software-as-a-service}, doi={10.1109/CloudCom.2014.128}} | G70: {=INDIRECT("Venues!C" & MATCH(B70,Venues!A:A,0))} -> IEEE
A71: 67 | B71: =Venues!A40 -> 38 | C71: Scheduling Concurrent Workflows in HPC Cloud through Exploiting Schedule Gaps | D71: 2011 | E71: Distributed Gap Search (DGS) | F71: inproceedings{67, author="Jiang, He-Jhan and Huang, Kuo-Chan and Chang, Hsi-Ya and Gu, Di-Syuan and Shih, Po-Jen", editor="Xiang, Yang and Cuzzocrea, Alfredo and Hobbs, Michael and Zhou, Wanlei", title="Scheduling Concurrent Workflows in HPC Cloud through Exploiting Schedule Gaps", booktitle="Algorithms and Architectures for Parallel Processing", year="2011", publisher="Springer Berlin Heidelberg", address="Berlin, Heidelberg", pages="282--293", abstract="Many large-scale scientific applications are usually constructed as workflows due to large amounts of interrelated computation and communication. Workflow scheduling has long been a research topic in parallel and distributed computing. However, most previous research focuses on single workflow scheduling. As cloud computing emerges, users can now have easy access to on-demand high performance computing resources, usually called HPC cloud. Since HPC cloud has to serve many users simultaneously, it is common that many workflows submitted from different users are running concurrently. Therefore, how to schedule concurrent workflows efficiently becomes an important issue in HPC cloud environments. Due to the dependency and communication costs between tasks in a workflow, there usually are gaps formed in the schedule of a workflow. In this paper, we propose a method which exploits such schedule gaps to efficiently schedule concurrent workflows in HPC cloud. The proposed scheduling method was evaluated with a series of simulation experiments and compared to the existing method in the literature. The results indicate that our method can deliver good performance and outperform the existing method significantly in terms of average makespan, up to 18{\%} performance improvement.", isbn="978-3-642-24650-0" } | G71: {=INDIRECT("Venues!C" & MATCH(B71,Venues!A:A,0))} -> Springer
A72: 68 | B72: =Venues!A41 -> 39 | C72: A Multiple QoS Constrained Scheduling Strategy of Multiple Workflows for Cloud Computing | D72: 2009 | E72: Multiple QoS constrained scheduling strategy of Multi-Workflows (MQMW) | F72: inproceedings{68, author={Xu, Meng and Cui, Lizhen and Wang, Haiyang and Bi, Yanbing}, booktitle={2009 IEEE International Symposium on Parallel and Distributed Processing with Applications}, title={A Multiple QoS Constrained Scheduling Strategy of Multiple Workflows for Cloud Computing}, year={2009}, volume={}, number={}, pages={629-634}, keywords={Processor scheduling;Cloud computing;Quality of service;Scheduling algorithm;Costs;Partitioning algorithms;Algorithm design and analysis;Distributed processing;Application software;Bismuth;Cloud Computing;Scheduling;Multiple QoS Requirements;Multiple Workflows}, doi={10.1109/ISPA.2009.95}} | G72: {=INDIRECT("Venues!C" & MATCH(B72,Venues!A:A,0))} -> IEEE
A73: 69 | B73: =Venues!A41 -> 39 | C73: Scheduling Multiple Workflows with Time Constraints onto Cloud Computing Resources | D73: 2019 | E73: Merge Concurrently Submitted Workflows(MCSW) | F73: inproceedings{69, author={Zheng, Wei and Shen, Lin and Bugingo, Emmanuel and Zhang, Dongzhan}, booktitle={2019 IEEE Intl Conf on Parallel & Distributed Processing with Applications, Big Data & Cloud Computing, Sustainable Computing & Communications, Social Computing & Networking (ISPA/BDCloud/SocialCom/SustainCom)}, title={Scheduling Multiple Workflows with Time Constraints onto Cloud Computing Resources}, year={2019}, volume={}, number={}, pages={572-579}, keywords={Task analysis;Processor scheduling;Cloud computing;Scheduling;Merging;Time factors;Resource management;Cloud computing;Multiple workflows;Constrained scheduling;Resources utilization}, doi={10.1109/ISPA-BDCloud-SustainCom-SocialCom48970.2019.00087}} | G73: {=INDIRECT("Venues!C" & MATCH(B73,Venues!A:A,0))} -> IEEE
A74: 70 | B74: =Venues!A42 -> 40 | C74: Executing Large Scale Scientific Workflow Ensembles in Public Clouds | D74: 2015 | E74: Distributed Elastic scientific Workflow Execution (DEWE v2) | F74: inproceedings{70, author={Jiang, Qingye and Lee, Young Choon and Zomaya, Albert Y.}, booktitle={2015 44th International Conference on Parallel Processing}, title={Executing Large Scale Scientific Workflow Ensembles in Public Clouds}, year={2015}, volume={}, number={}, pages={520-529}, keywords={Cloud computing;Scheduling;Processor scheduling;Australia;Electronic mail;Information technology;Engines;workflow ensemble;cloud computing;parallel computing;resource provisioning}, doi={10.1109/ICPP.2015.61}} | G74: {=INDIRECT("Venues!C" & MATCH(B74,Venues!A:A,0))} -> IEEE
A75: 71 | B75: =Venues!A43 -> 41 | C75: Cost-Aware Dynamic Multi-Workflow Scheduling in Cloud Data Center Using Evolutionary Reinforcement Learning | D75: 2022 | E75: Evolutionary Strategy based Reinforcement Learning (ES-RL) | F75: inproceedings{71, author="Huang, Victoria and Wang, Chen and Ma, Hui and Chen, Gang and Christopher, Kameron", editor="Troya, Javier and Medjahed, Brahim and Piattini, Mario and Yao, Lina and Fern{\'a}ndez, Pablo and Ruiz-Cort{\'e}s, Antonio", title="Cost-Aware Dynamic Multi-Workflow Scheduling in Cloud Data Center Using Evolutionary Reinforcement Learning", booktitle="Service-Oriented Computing", year="2022", publisher="Springer Nature Switzerland", address="Cham", pages="449--464", abstract="The Dynamic Multi-Workflow Scheduling (DMWS) problem aims to allocate highly complex tasks modeled as workflows to cloud resources while optimizing workflow brokers' interests. A workflow broker offers workflow execution services to end-users with agreed Service Level Agreements (SLA) while reducing its total VM rental fees in the meantime. Most existing DMWS-related research works focus on minimizing the workflow makespan by using either heuristics or hyper-heuristics techniques. However, these techniques were either designed for static workflow scheduling based on prior workflow information and/or the simplified cloud environment. In this paper, the DMWS problem is formulated to collectively minimize VM rental fees and SLA violation penalties. Moreover, we introduce a novel priority-based deep neural network scheduling policy that can flexibly adapt to a changing number of VMs and workflows. To train the new policy, a new Evolutionary Strategy based Reinforcement Learning (ES-RL) is developed and implemented. Different from gradient-based deep reinforcement learning algorithms, ES-RL has its advances in effectively training population-based and generally applicable policies in parallel as well as robustness to hyper-parameter settings. Our experiments with real-world datasets show that ES-RL can effectively train scheduling policies that can significantly reduce the costs by more than 90{\%} compared to the state-of-the-art scheduling policies.", isbn="978-3-031-20984-0" } | G75: {=INDIRECT("Venues!C" & MATCH(B75,Venues!A:A,0))} -> Springer
A76: 72 | B76: =Venues!A44 -> 42 | C76: Transfer Learning Assisted GPHH for Dynamic Multi-Workflow Scheduling in Cloud Computing | D76: 2022 | E76: Transfer Learning assisted Genetic Programming Hyper-Heuristic (TL-GPHH) | F76: inproceedings{72, author="Escott, Kirita-Rose and Ma, Hui and Chen, Gang", editor="Long, Guodong and Yu, Xinghuo and Wang, Sen", title="Transfer Learning Assisted GPHH for Dynamic Multi-Workflow Scheduling in Cloud Computing", booktitle="AI 2021: Advances in Artificial Intelligence", year="2022", publisher="Springer International Publishing", address="Cham", pages="440--451", abstract="Dynamic Multi-Workflow Scheduling (DWS) in cloud is a challenging optimisation due to the dynamic nature of the problem. It requires complex mapping decisions to be made under unknown dynamic events. Genetic Programming Hyper-Heuristic (GPHH) has been successfully applied to generate scheduling heuristics for DWS due to its flexible representation. However, the simulation-based evaluation is computationally expensive due to calculations required by individuals to make decisions in the simulation. To improve efficiency, this paper proposes a novel Transfer Learning (TL) Assisted GPHH (TL-GPHH). Specifically, TL-GPHH is designed and compared with Non-Assisted GPHH to generate effective heuristic rules in less time. The results show that the proposed algorithm generates heuristics that can minimise makespan in more scenarios than Non-Assisted GPHH and other state-of-the-art heuristics. Moreover, the proposed algorithm can reduce the computational costs of GP without sacrificing the performance.", isbn="978-3-030-97546-3" } | G76: {=INDIRECT("Venues!C" & MATCH(B76,Venues!A:A,0))} -> Springer
A77: 73 | B77: =Venues!A45 -> 43 | C77: Security-Aware Scheduling of Multiple Scientific Workflows in Cloud | D77: 2024 | E77: OptReUse | F77: inproceedings{73, author="Roy, Shubhro and Gharote, Mangesh and Ramamurthy, Arun and Pawar, Anand and Lodha, Sachin", editor="van Steen, Maarten and Ferguson, Donald and Pahl, Claus", title="Security-Aware Scheduling of Multiple Scientific Workflows in Cloud", booktitle="Cloud Computing and Services Science", year="2024", publisher="Springer Nature Switzerland", address="Cham", pages="1--24", abstract="With the advent of cloud computing benefits of unlimited computing resources at low cost and flexibility due to virtualization technology, has attracted attention for executing complex scientific processes. The scientific workflows comprise of interdependent and heterogenous tasks. The cloud provides different instances of VMs (computing, memory, storage) and different security services (such as authentication, integrity, confidentiality) for secure processing to this complex workflow. It becomes challenging to select the right combination of VM instance type to optimize overall cost and processing duration (makespan) and selecting the right combination of security levels to keep the risk rate within permissible limits.", isbn="978-3-031-68165-3" } | G77: {=INDIRECT("Venues!C" & MATCH(B77,Venues!A:A,0))} -> Springer
A78: 74 | B78: =Venues!A3 -> 1 | C78: SpotDAG: An RL-Based Algorithm for DAG Workflow Scheduling in Heterogeneous Cloud Environments | D78: 2024 | E78: SpotDAG | F78: article{74, author={Lin, Liduo and Pan, Li and Liu, Shijun}, journal={IEEE Transactions on Services Computing}, title={SpotDAG: An RL-Based Algorithm for DAG Workflow Scheduling in Heterogeneous Cloud Environments}, year={2024}, volume={17}, number={5}, pages={2904-2917}, keywords={Data processing;Job shop scheduling;Costs;Cloud computing;Optimization;Task analysis;Data models;Heterogeneous cloud environments;spot instance;on-demand instance;IaaS}, doi={10.1109/TSC.2024.3422828}} | G78: IEEE

Sheet Negotiation and Pricing Taxonom
A1: PID | C1: Negotiation and Pricing
C2: Qos Requirements | E2: Workflow Arrival | I2: Negotiation | K2: Pricing
C3: Multi-Criteria | D3: Constrained | E3: Online | F3: Batch | G3: Ensemble | H3: Periodic | I3: Static | J3: Dynamic | K3: Pre-pricing | L3: Post-pricing
A5: =Papers!A3 -> 1 | D5: P | H5: P
A6: =Papers!A4 -> 2 | D6: P | E6: P | I6: P | K6: P | L6: P
A7: =Papers!A5 -> 3 | D7: P | E7: P
A8: =Papers!A6 -> 4 | D8: P | E8: P
A9: =Papers!A7 -> 5 | D9: P | H9: P
A10: =Papers!A8 -> 6 | D10: P | E10: P
A11: =Papers!A9 -> 7 | C11: P | E11: P
A12: =Papers!A10 -> 8 | D12: P | E12: P
A13: =Papers!A11 -> 9 | D13: P | E13: P
A14: =Papers!A12 -> 10 | C14: P | E14: P
A15: =Papers!A13 -> 11 | D15: P | E15: P
A16: =Papers!A14 -> 12 | D16: P | E16: P
A17: =Papers!A15 -> 13 | D17: P | E17: P
A18: =Papers!A16 -> 14 | D18: P | E18: P
A19: =Papers!A17 -> 15 | D19: P | F19: P
A20: =Papers!A18 -> 16 | D20: P | E20: P
A21: =Papers!A19 -> 17 | C21: P | F21: P
A22: =Papers!A20 -> 18 | D22: P | F22: P
A23: =Papers!A21 -> 19 | D23: P | E23: P
A24: =Papers!A22 -> 20 | D24: P | G24: P
A25: =Papers!A23 -> 21 | D25: P | G25: P
A26: =Papers!A24 -> 21-b | D26: P | G26: P
A27: =Papers!A25 -> 22 | D27: P | E27: P
A28: =Papers!A26 -> 23 | D28: P | E28: P
A29: =Papers!A27 -> 24 | D29: P | E29: P
A30: =Papers!A28 -> 25 | D30: P | F30: P
A31: =Papers!A29 -> 26 | D31: P | E31: P
A32: =Papers!A30 -> 27 | D32: P | E32: P
A33: =Papers!A31 -> 28 | D33: P | E33: P
A34: =Papers!A32 -> 29 | D34: P | E34: P
A35: =Papers!A33 -> 30 | D35: P | E35: P
A36: =Papers!A34 -> 31 | D36: P | E36: P
A37: =Papers!A35 -> 32 | C37: P | F37: P
A38: =Papers!A36 -> 33 | C38: P | F38: P
A39: =Papers!A37 -> 34 | C39: P | F39: P
A40: =Papers!A38 -> 35 | D40: P | F40: P
A41: =Papers!A39 -> 36 | C41: P | F41: P
A42: =Papers!A40 -> 37 | D42: P | E42: P
A43: =Papers!A41 -> 38 | D43: P | E43: P
A44: =Papers!A42 -> 39 | D44: P | E44: P
A45: =Papers!A43 -> 40 | C45: P | F45: P
A46: =Papers!A44 -> 41 | D46: P | E46: P
A47: =Papers!A45 -> 42 | D47: P | E47: P
A48: =Papers!A46 -> 43 | D48: P | E48: P
A49: =Papers!A47 -> 44 | C49: P | F49: P
A50: =Papers!A48 -> 45 | D50: P | E50: P
A51: =Papers!A49 -> 46 | C51: P | D51: P | F51: P
A52: =Papers!A50 -> 47 | C52: P | F52: P
A53: =Papers!A51 -> 48 | D53: P | F53: P
A54: =Papers!A52 -> 49 | C54: P | F54: P
A55: =Papers!A53 -> 49-b | C55: P | E55: P
A56: =Papers!A54 -> 50 | D56: P | F56: P
A57: =Papers!A55 -> 51 | C57: P | D57: P | E57: P
A58: =Papers!A56 -> 52 | D58: P | E58: P
A59: =Papers!A57 -> 53 | D59: P | G59: P
A60: =Papers!A58 -> 54 | D60: P | E60: P
A61: =Papers!A59 -> 55 | D61: P | E61: P | G61: P
A62: =Papers!A60 -> 56 | C62: P | F62: P
A63: =Papers!A61 -> 57 | D63: P | E63: P
A64: =Papers!A62 -> 58 | C64: P | D64: P | F64: P
A65: =Papers!A63 -> 59 | C65: P | E65: P
A66: =Papers!A64 -> 60 | D66: P | E66: P
A67: =Papers!A65 -> 61 | C67: P | E67: P
A68: =Papers!A66 -> 62 | C68: P | E68: P
A69: =Papers!A67 -> 63 | D69: P | E69: P
A70: =Papers!A68 -> 64 | D70: P | E70: P
A71: =Papers!A69 -> 65 | C71: P | E71: P
A72: =Papers!A70 -> 66 | D72: P | E72: P
A73: =Papers!A71 -> 67 | C73: P | E73: P
A74: =Papers!A72 -> 68 | D74: P | E74: P
A75: =Papers!A73 -> 69 | D75: P | E75: P
A76: =Papers!A74 -> 70 | C76: P | G76: P
A77: =Papers!A75 -> 71 | D77: P | E77: P
A78: =Papers!A76 -> 72 | C78: P | E78: P
A79: =Papers!A77 -> 73 | D79: P | E79: P
A80: =Papers!A78 -> 74 | D80: P | E80: P

Sheet Task Scheduler Taxonomy
A1: PID | C1: Task Scheduling
C2: Task Type | E2: Task Concurrency | G2: Task Time Estimation | J2: Data Transmission | L2: Scheduling Criteria | T2: Scheduling Type | X2: Scheduling Strategy
C3: Rigid | D3: Flexible | E3: Single | F3: Multiple | G3: Fixed | H3: Probabilistic | I3: Fuzzy | J3: Direct | K3: Indirect | L3: Time | M3: Cost | N3: Security | O3: Privacy | P3: Reliability | Q3: Fairness | R3: Energy | S3: Utilization | T3: Static | V3: Dynamic | X3: Heuristic | Y3: Meta-heuristic | Z3: Game Theory | AA3: Reinforcement Learning | AB3: MCDM | AC3: Mathematical Optimization
T4: One-by-one | U4: Combined | V4: Immediate | W4: Periodic
A6: =Papers!A3 -> 1 | C6: P | F6: P | H6: P | K6: P | L6: P | M6: P | U6: P | W6: P | X6: P
A7: =Papers!A4 -> 2 | C7: P | F7: P | H7: P | K7: P | L7: P | M7: P | W7: P | X7: P
A8: =Papers!A5 -> 3 | D8: P | E8: P | G8: P | J8: P | L8: P | M8: P | U8: P | Y8: P
A9: =Papers!A6 -> 4 | D9: P | E9: P | H9: P | J9: P | L9: P | M9: P | Q9: P | S9: P | V9: P | X9: P
A10: =Papers!A7 -> 5 | D10: P | E10: P | G10: P | L10: P | M10: P | U10: P | X10: P
A11: =Papers!A8 -> 6 | D11: P | E11: P | H11: P | J11: P | L11: P | M11: P | V11: P | X11: P
A12: =Papers!A9 -> 7 | D12: P | E12: P | G12: P | L12: P | M12: P | V12: P | AA12: P
A13: =Papers!A10 -> 8 | D13: P | E13: P | H13: P | K13: P | L13: P | M13: P | S13: P | V13: P | X13: P
A14: =Papers!A11 -> 9 | D14: P | E14: P | G14: P | J14: P | L14: P | M14: P | P14: P | R14: P | V14: P | X14: P
A15: =Papers!A12 -> 10 | D15: P | E15: P | G15: P | J15: P | L15: P | M15: P | V15: P | AB15: P
A16: =Papers!A13 -> 11 | D16: P | E16: P | H16: P | J16: P | L16: P | S16: P | V16: P | X16: P
A17: =Papers!A14 -> 12 | D17: P | E17: P | G17: P | J17: P | L17: P | M17: P | S17: P | V17: P | X17: P
A18: =Papers!A15 -> 13 | D18: P | E18: P | G18: P | K18: P | L18: P | M18: P | V18: P | X18: P
A19: =Papers!A16 -> 14 | D19: P | E19: P | H19: P | J19: P | L19: P | M19: P | V19: P | X19: P
A20: =Papers!A17 -> 15 | C20: P | E20: P | G20: P | L20: P | M20: P | Q20: P | T20: P | X20: P
A21: =Papers!A18 -> 16 | C21: P | E21: P | I21: P | K21: P | L21: P | M21: P | W21: P | X21: P
A22: =Papers!A19 -> 17 | D22: P | E22: P | G22: P | L22: P | M22: P | Q22: P | U22: P | Z22: P
A23: =Papers!A20 -> 18 | D23: P | E23: P | G23: P | L23: P | M23: P | T23: P | Y23: P
A24: =Papers!A21 -> 19 | D24: P | E24: P | G24: P | K24: P | L24: P | M24: P | W24: P | X24: P
A25: =Papers!A22 -> 20 | C25: P | E25: P | G25: P | K25: P | L25: P | M25: P | W25: P | X25: P
A26: =Papers!A23 -> 21 | C26: P | E26: P | H26: P | K26: P | L26: P | M26: P | V26: P | X26: P
A27: =Papers!A24 -> 21-b | C27: P | E27: P | H27: P | K27: P | L27: P | M27: P | T27: P | X27: P
A28: =Papers!A25 -> 22 | D28: P | E28: P | G28: P | K28: P | L28: P | M28: P | W28: P | X28: P
A29: =Papers!A26 -> 23 | D29: P | E29: P | G29: P | J29: P | L29: P | M29: P | V29: P | X29: P
A30: =Papers!A27 -> 24 | D30: P | E30: P | H30: P | K30: P | L30: P | M30: P | R30: P | V30: P | X30: P
A31: =Papers!A28 -> 25 | D31: P | E31: P | G31: P | L31: P | S31: P | V31: P | X31: P
A32: =Papers!A29 -> 26 | D32: P | E32: P | G32: P | K32: P | L32: P | M32: P | V32: P | AB32: P
A33: =Papers!A30 -> 27 | D33: P | E33: P | G33: P | J33: P | L33: P | M33: P | V33: P | X33: P
A34: =Papers!A31 -> 28 | D34: P | E34: P | G34: P | K34: P | M34: P | S34: P | V34: P | X34: P
A35: =Papers!A32 -> 29 | D35: P | E35: P | G35: P | J35: P | L35: P | M35: P | S35: P | V35: P | AB35: P
A36: =Papers!A33 -> 30 | D36: P | E36: P | H36: P | J36: P | L36: P | M36: P | V36: P | X36: P
A37: =Papers!A34 -> 31 | D37: P | E37: P | H37: P | K37: P | L37: P | M37: P | V37: P | X37: P
A38: =Papers!A35 -> 32 | D38: P | F38: P | G38: P | J38: P | L38: P | M38: P | R38: P | S38: P | U38: P | X38: P
A39: =Papers!A36 -> 33 | D39: P | E39: P | G39: P | K39: P | L39: P | M39: P | W39: P | AA39: P
A40: =Papers!A37 -> 34 | D40: P | E40: P | G40: P | J40: P | L40: P | N40: P | P40: P | U40: P | X40: P
A41: =Papers!A38 -> 35 | D41: P | E41: P | G41: P | L41: P | M41: P | N41: P | T41: P | X41: P
A42: =Papers!A39 -> 36 | D42: P | E42: P | G42: P | J42: P | L42: P | M42: P | Q42: P | T42: P | X42: P | Y42: P
A43: =Papers!A40 -> 37 | D43: P | E43: P | G43: P | K43: P | L43: P | M43: P | T43: P | X43: P
A44: =Papers!A41 -> 38 | D44: P | E44: P | H44: P | J44: P | L44: P | M44: P | V44: P | X44: P
A45: =Papers!A42 -> 39 | D45: P | E45: P | G45: P | L45: P | M45: P | V45: P | Y45: P
A46: =Papers!A43 -> 40 | D46: P | E46: P | G46: P | J46: P | L46: P | S46: P | U46: P | X46: P
A47: =Papers!A44 -> 41 | D47: P | F47: P | G47: P | K47: P | L47: P | M47: P | S47: P | W47: P | X47: P
A48: =Papers!A45 -> 42 | D48: P | E48: P | H48: P | J48: P | L48: P | M48: P | S48: P | V48: P | W48: P | X48: P
A49: =Papers!A46 -> 43 | D49: P | E49: P | G49: P | K49: P | L49: P | M49: P | P49: P | V49: P | X49: P
A50: =Papers!A47 -> 44 | D50: P | E50: P | G50: P | J50: P | L50: P | M50: P | U50: P | Y50: P
A51: =Papers!A48 -> 45 | D51: P | E51: P | G51: P | J51: P | L51: P | S51: P | T51: P | X51: P
A52: =Papers!A49 -> 46 | D52: P | E52: P | G52: P | J52: P | L52: P | M52: P | R52: P | U52: P | Y52: P
A53: =Papers!A50 -> 47 | D53: P | E53: P | G53: P | J53: P | L53: P | M53: P | U53: P | Y53: P
A54: =Papers!A51 -> 48 | D54: P | E54: P | G54: P | J54: P | L54: P | M54: P | U54: P | Y54: P
A55: =Papers!A52 -> 49 | D55: P | E55: P | G55: P | J55: P | L55: P | M55: P | O55: P | R55: P | U55: P | Y55: P
A56: =Papers!A53 -> 49-b | D56: P | E56: P | G56: P | J56: P | L56: P | M56: P | O56: P | R56: P | T56: P | X56: P
A57: =Papers!A54 -> 50 | D57: P | E57: P | G57: P | J57: P | L57: P | M57: P | U57: P | Y57: P
A58: =Papers!A55 -> 51 | D58: P | E58: P | G58: P | K58: P | L58: P | M58: P | S58: P | V58: P | X58: P
A59: =Papers!A56 -> 52 | D59: P | E59: P | G59: P | J59: P | L59: P | M59: P | V59: P | X59: P
A60: =Papers!A57 -> 53 | D60: P | E60: P | G60: P | J60: P | L60: P | M60: P | V60: P | X60: P
A61: =Papers!A58 -> 54 | D61: P | E61: P | H61: P | K61: P | L61: P | M61: P | T61: P | X61: P
A62: =Papers!A59 -> 55 | D62: P | E62: P | H62: P | J62: P | L62: P | M62: P | T62: P | V62: P | X62: P
A63: =Papers!A60 -> 56 | D63: P | E63: P | G63: P | L63: P | M63: P | Q63: P | U63: P | Y63: P
A64: =Papers!A61 -> 57 | D64: P | E64: P | G64: P | J64: P | L64: P | M64: P | V64: P | Y64: P
A65: =Papers!A62 -> 58 | D65: P | F65: P | G65: P | J65: P | L65: P | M65: P | S65: P | U65: P | AC65: P
A66: =Papers!A63 -> 59 | D66: P | E66: P | G66: P | L66: P | V66: P | AA66: P
A67: =Papers!A64 -> 60 | D67: P | F67: P | G67: P | L67: P | M67: P | T67: P | Y67: P | AA67: P
A68: =Papers!A65 -> 61 | C68: P | E68: P | G68: P | K68: P | L68: P | M68: P | U68: P | V68: P | X68: P
A69: =Papers!A66 -> 62 | C69: P | F69: P | G69: P | J69: P | L69: P | V69: P | X69: P
A70: =Papers!A67 -> 63 | D70: P | E70: P | G70: P | L70: P | M70: P | V70: P | AA70: P
A71: =Papers!A68 -> 64 | D71: P | E71: P | I71: P | J71: P | L71: P | M71: P | V71: P | X71: P
A72: =Papers!A69 -> 65 | D72: P | E72: P | H72: P | J72: P | L72: P | M72: P | S72: P | V72: P | X72: P
A73: =Papers!A70 -> 66 | D73: P | E73: P | G73: P | K73: P | L73: P | M73: P | O73: P | U73: P | X73: P
A74: =Papers!A71 -> 67 | D74: P | E74: P | G74: P | J74: P | L74: P | S74: P | T74: P | X74: P
A75: =Papers!A72 -> 68 | D75: P | E75: P | G75: P | L75: P | M75: P | V75: P | X75: P
A76: =Papers!A73 -> 69 | C76: P | E76: P | G76: P | L76: P | S76: P | T76: P | U76: P | X76: P
A77: =Papers!A74 -> 70 | C77: P | E77: P | G77: P | K77: P | L77: P | M77: P | S77: P | V77: P | X77: P
A78: =Papers!A75 -> 71 | D78: P | E78: P | G78: P | L78: P | M78: P | V78: P | Y78: P | AA78: P
A79: =Papers!A76 -> 72 | D79: P | E79: P | G79: P | L79: P | V79: P | Y79: P
A80: =Papers!A77 -> 73 | D80: P | E80: P | G80: P | J80: P | L80: P | M80: P | N80: P | U80: P | X80: P | Y80: P
A81: =Papers!A78 -> 74 | C81: P | F81: P | H81: P | L81: P | M81: P | W81: P | AA81: P

Sheet Resource Provisioner Taxonomy
A1: PID | C1: Resource Provisioning
C2: Resource Type | F2: Resource Diversity | H2: Resource Pricing | K2: Provisioning Timing | M2: Provisining Delay | O2: Deployment Model
C3: VM | D3: Container | E3: Function | F3: Heterogeneous | G3: Homogeneous | H3: On-demand | I3: Spot | J3: Reserved | K3: As-needed | L3: Periodic | M3: Delay-aware | N3: Instantaneous | O3: Single-Cloud | P3: Multi-Cloud | Q3: Hybrid Cloud
A5: =Papers!A3 -> 1 | D5: P | G5: P | H5: P | J5: P | K5: P | M5: P | O5: P
A6: =Papers!A4 -> 2 | D6: P | F6: P | H6: P | I6: P | L6: P | M6: P | O6: P
A7: =Papers!A5 -> 3 | C7: P | F7: P | H7: P | K7: P | N7: P | O7: P
A8: =Papers!A6 -> 4 | C8: P | F8: P | H8: P | K8: P | M8: P | O8: P
A9: =Papers!A7 -> 5 | C9: P | F9: P | J9: P | L9: P | N9: P | O9: P
A10: =Papers!A8 -> 6 | C10: P | F10: P | H10: P | K10: P | N10: P | O10: P
A11: =Papers!A9 -> 7 | C11: P | F11: P | H11: P | K11: P | N11: P | O11: P
A12: =Papers!A10 -> 8 | C12: P | F12: P | H12: P | K12: P | N12: P | O12: P
A13: =Papers!A11 -> 9 | C13: P | F13: P | H13: P | K13: P | N13: P | P13: P
A14: =Papers!A12 -> 10 | C14: P | F14: P | H14: P | K14: P | N14: P | O14: P
A15: =Papers!A13 -> 11 | C15: P | F15: P | J15: P | O15: P
A16: =Papers!A14 -> 12 | C16: P | F16: P | H16: P | K16: P | M16: P | O16: P
A17: =Papers!A15 -> 13 | C17: P | F17: P | H17: P | K17: P | M17: P | O17: P
A18: =Papers!A16 -> 14 | C18: P | F18: P | H18: P | O18: P
A19: =Papers!A17 -> 15 | C19: P | F19: P | H19: P | K19: P | N19: P | O19: P
A20: =Papers!A18 -> 16 | C20: P | G20: P | H20: P | J20: P | K20: P | N20: P | O20: P
A21: =Papers!A19 -> 17 | C21: P | F21: P | H21: P | P21: P
A22: =Papers!A20 -> 18 | C22: P | F22: P | H22: P | K22: P | N22: P | O22: P
A23: =Papers!A21 -> 19 | D23: P | F23: P | H23: P | K23: P | M23: P | O23: P
A24: =Papers!A22 -> 20 | C24: P | G24: P | H24: P | I24: P | L24: P | M24: P | O24: P
A25: =Papers!A23 -> 21 | C25: P | G25: P | H25: P | L25: P | M25: P | O25: P
A26: =Papers!A24 -> 21-b | C26: P | G26: P | H26: P | K26: P | M26: P | O26: P
A27: =Papers!A25 -> 22 | D27: P | F27: P | H27: P | K27: P | M27: P | O27: P
A28: =Papers!A26 -> 23 | C28: P | F28: P | H28: P | K28: P | N28: P | O28: P
A29: =Papers!A27 -> 24 | D29: P | F29: P | H29: P | K29: P | M29: P | O29: P
A30: =Papers!A28 -> 25 | C30: P | F30: P | H30: P | K30: P | N30: P | O30: P
A31: =Papers!A29 -> 26 | C31: P | F31: P | H31: P | K31: P | N31: P | O31: P
A32: =Papers!A30 -> 27 | C32: P | F32: P | J32: P | O32: P
A33: =Papers!A31 -> 28 | C33: P | F33: P | J33: P | O33: P
A34: =Papers!A32 -> 29 | C34: P | F34: P | H34: P | K34: P | M34: P | O34: P
A35: =Papers!A33 -> 30 | C35: P | F35: P | H35: P | K35: P | M35: P | P35: P
A36: =Papers!A34 -> 31 | D36: P | F36: P | H36: P | K36: P | M36: P | O36: P
A37: =Papers!A35 -> 32 | D37: P | F37: P | H37: P | L37: P | M37: P | O37: P
A38: =Papers!A36 -> 33 | C38: P | F38: P | H38: P | O38: P
A39: =Papers!A37 -> 34 | C39: P | F39: P | H39: P | K39: P | N39: P | O39: P
A40: =Papers!A38 -> 35 | C40: P | F40: P | H40: P | P40: P
A41: =Papers!A39 -> 36 | C41: P | F41: P | J41: P | O41: P
A42: =Papers!A40 -> 37 | C42: P | F42: P | H42: P | O42: P
A43: =Papers!A41 -> 38 | C43: P | F43: P | H43: P | K43: P | N43: P | O43: P
A44: =Papers!A42 -> 39 | C44: P | F44: P | H44: P | K44: P | O44: P
A45: =Papers!A43 -> 40 | C45: P | F45: P | J45: P | O45: P
A46: =Papers!A44 -> 41 | D46: P | F46: P | H46: P | K46: P | M46: P | O46: P
A47: =Papers!A45 -> 42 | C47: P | F47: P | H47: P | K47: P | N47: P | O47: P
A48: =Papers!A46 -> 43 | D48: P | F48: P | H48: P | I48: P | O48: P
A49: =Papers!A47 -> 44 | C49: P | F49: P | H49: P | K49: P | N49: P | O49: P
A50: =Papers!A48 -> 45 | C50: P | F50: P | H50: P | L50: P | M50: P | O50: P
A51: =Papers!A49 -> 46 | C51: P | F51: P | H51: P | K51: P | M51: P | Q51: P
A52: =Papers!A50 -> 47 | C52: P | F52: P | H52: P | K52: P | O52: P
A53: =Papers!A51 -> 48 | C53: P | F53: P | H53: P | K53: P | O53: P
A54: =Papers!A52 -> 49 | C54: P | F54: P | H54: P | K54: P | M54: P | Q54: P
A55: =Papers!A53 -> 49-b | C55: P | F55: P | H55: P | K55: P | M55: P | Q55: P
A56: =Papers!A54 -> 50 | C56: P | F56: P | H56: P | K56: P | N56: P | O56: P
A57: =Papers!A55 -> 51 | C57: P | F57: P | H57: P | L57: P | N57: P | P57: P
A58: =Papers!A56 -> 52 | C58: P | F58: P | H58: P | O58: P
A59: =Papers!A57 -> 53 | C59: P | F59: P | H59: P | I59: P | K59: P | M59: P | O59: P
A60: =Papers!A58 -> 54 | C60: P | F60: P | H60: P | I60: P | K60: P | N60: P | O60: P
A61: =Papers!A59 -> 55 | C61: P | F61: P | H61: P | K61: P | N61: P | O61: P | P61: P
A62: =Papers!A60 -> 56 | C62: P | F62: P | H62: P | K62: P | N62: P | O62: P
A63: =Papers!A61 -> 57 | C63: P | E63: P | F63: P | H63: P | K63: P | M63: P | P63: P
A64: =Papers!A62 -> 58 | D64: P | F64: P | H64: P | L64: P | M64: P | O64: P
A65: =Papers!A63 -> 59 | C65: P | F65: P | J65: P | O65: P
A66: =Papers!A64 -> 60 | C66: P | F66: P | J66: P | O66: P
A67: =Papers!A65 -> 61 | C67: P | F67: P | H67: P | K67: P | N67: P | O67: P
A68: =Papers!A66 -> 62 | C68: P | G68: P | J68: P | O68: P
A69: =Papers!A67 -> 63 | C69: P | F69: P | H69: P | K69: P | N69: P | O69: P
A70: =Papers!A68 -> 64 | C70: P | F70: P | H70: P | K70: P | N70: P | O70: P
A71: =Papers!A69 -> 65 | C71: P | F71: P | H71: P | K71: P | N71: P | O71: P
A72: =Papers!A70 -> 66 | C72: P | F72: P | H72: P | K72: P | N72: P | Q72: P
A73: =Papers!A71 -> 67 | C73: P | F73: P | J73: P | O73: P
A74: =Papers!A72 -> 68 | C74: P | F74: P | H74: P | K74: P | O74: P
A75: =Papers!A73 -> 69 | C75: P | G75: P | J75: P | O75: P
A76: =Papers!A74 -> 70 | C76: P | G76: P | H76: P | K76: P | O76: P
A77: =Papers!A75 -> 71 | C77: P | F77: P | H77: P | K77: P | N77: P | O77: P
A78: =Papers!A76 -> 72 | C78: P | F78: P | J78: P | O78: P
A79: =Papers!A77 -> 73 | C79: P | F79: P | H79: P | K79: P | N79: P | O79: P
A80: =Papers!A78 -> 74 | C80: P | F80: P | H80: P | I80: P | K80: P | N80: P | O80: P

Sheet Monitoring and Fault Tolerance 
A1: PID | C1: Monitoring and Fault Tolerance
C2: Checkpointing | D2: Re-execution | E2: Replication
A4: =Papers!A3 -> 1
A5: =Papers!A4 -> 2 | C5: P
A6: =Papers!A5 -> 3
A7: =Papers!A6 -> 4
A8: =Papers!A7 -> 5
A9: =Papers!A8 -> 6
A10: =Papers!A9 -> 7
A11: =Papers!A10 -> 8
A12: =Papers!A11 -> 9 | E12: P
A13: =Papers!A12 -> 10
A14: =Papers!A13 -> 11
A15: =Papers!A14 -> 12
A16: =Papers!A15 -> 13
A17: =Papers!A16 -> 14
A18: =Papers!A17 -> 15
A19: =Papers!A18 -> 16
A20: =Papers!A19 -> 17
A21: =Papers!A20 -> 18 | C21: P
A22: =Papers!A21 -> 19
A23: =Papers!A22 -> 20 | C23: P
A24: =Papers!A23 -> 21 | D24: P
A25: =Papers!A24 -> 21-b
A26: =Papers!A25 -> 22
A27: =Papers!A26 -> 23
A28: =Papers!A27 -> 24
A29: =Papers!A28 -> 25
A30: =Papers!A29 -> 26
A31: =Papers!A30 -> 27
A32: =Papers!A31 -> 28
A33: =Papers!A32 -> 29
A34: =Papers!A33 -> 30 | C34: P
A35: =Papers!A34 -> 31
A36: =Papers!A35 -> 32
A37: =Papers!A36 -> 33
A38: =Papers!A37 -> 34
A39: =Papers!A38 -> 35
A40: =Papers!A39 -> 36
A41: =Papers!A40 -> 37 | D41: P
A42: =Papers!A41 -> 38
A43: =Papers!A42 -> 39
A44: =Papers!A43 -> 40
A45: =Papers!A44 -> 41
A46: =Papers!A45 -> 42
A47: =Papers!A46 -> 43 | D47: P
A48: =Papers!A47 -> 44
A49: =Papers!A48 -> 45
A50: =Papers!A49 -> 46
A51: =Papers!A50 -> 47
A52: =Papers!A51 -> 48
A53: =Papers!A52 -> 49
A54: =Papers!A53 -> 49-b
A55: =Papers!A54 -> 50
A56: =Papers!A55 -> 51
A57: =Papers!A56 -> 52
A58: =Papers!A57 -> 53 | D58: P | E58: P
A59: =Papers!A58 -> 54 | D59: P
A60: =Papers!A59 -> 55
A61: =Papers!A60 -> 56
A62: =Papers!A61 -> 57
A63: =Papers!A62 -> 58
A64: =Papers!A63 -> 59
A65: =Papers!A64 -> 60
A66: =Papers!A65 -> 61
A67: =Papers!A66 -> 62
A68: =Papers!A67 -> 63
A69: =Papers!A68 -> 64
A70: =Papers!A69 -> 65
A71: =Papers!A70 -> 66
... A74: =Papers!A73 -> 69
A75: =Papers!A74 -> 70 | D75: P
A76: =Papers!A75 -> 71
A77: =Papers!A76 -> 72
A78: =Papers!A77 -> 73 | D78: P
A79: =Papers!A78 -> 74
